{
  "saved_at_utc": "2026-07-12T18:36:41+00:00",
  "source_url": "https://feargreedmeter.com/top-100-most-popular-meme-stocks-today",
  "rows_count": 100,
  "rows": [
    {
      "fetched_at_local": "2026-07-12T20:36:41+02:00",
      "fetched_at_utc": "2026-07-12T18:36:41+00:00",
      "rank": 1,
      "ticker": "SPY",
      "company_name": "SPDR S&P 500 ETF Trust",
      "upvotes": 364,
      "mentions": 63,
      "mention_change": -101,
      "source_url": "https://feargreedmeter.com/top-100-most-popular-meme-stocks-today",
      "raw_text": "# 1 . SPY SPDR S&P 500 ETF Trust 364 63 -101"
    },
    {
      "fetched_at_local": "2026-07-12T20:36:41+02:00",
      "fetched_at_utc": "2026-07-12T18:36:41+00:00",
      "rank": 2,
      "ticker": "MSFT",
      "company_name": "Microsoft",
      "upvotes": 512,
      "mentions": 44,
      "mention_change": -40,
      "source_url": "https://feargreedmeter.com/top-100-most-popular-meme-stocks-today",
      "raw_text": "# 2 . MSFT Microsoft 512 44 -40"
    },
    {
      "fetched_at_local": "2026-07-12T20:36:41+02:00",
      "fetched_at_utc": "2026-07-12T18:36:41+00:00",
      "rank": 3,
      "ticker": "SPCX",
      "company_name": "SpaceX",
      "upvotes": 841,
      "mentions": 35,
      "mention_change": -52,
      "source_url": "https://feargreedmeter.com/top-100-most-popular-meme-stocks-today",
      "raw_text": "# 3 . SPCX SpaceX 841 35 -52"
    },
    {
      "fetched_at_local": "2026-07-12T20:36:41+02:00",
      "fetched_at_utc": "2026-07-12T18:36:41+00:00",
      "rank": 4,
      "ticker": "MU",
      "company_name": "Micron Technology",
      "upvotes": 142,
      "mentions": 30,
      "mention_change": -146,
      "source_url": "https://feargreedmeter.com/top-100-most-popular-meme-stocks-today",
      "raw_text": "# 4 . MU Micron Technology 142 30 -146"
    },
    {
      "fetched_at_local": "2026-07-12T20:36:41+02:00",
      "fetched_at_utc": "2026-07-12T18:36:41+00:00",
      "rank": 5,
      "ticker": "NVDA",
      "company_name": "NVIDIA",
      "upvotes": 143,
      "mentions": 24,
      "mention_change": -38,
      "source_url": "https://feargreedmeter.com/top-100-most-popular-meme-stocks-today",
      "raw_text": "# 5 . NVDA NVIDIA 143 24 -38"
    },
    {
      "fetched_at_local": "2026-07-12T20:36:41+02:00",
      "fetched_at_utc": "2026-07-12T18:36:41+00:00",
      "rank": 6,
      "ticker": "DTE",
      "company_name": "DTE Energy",
      "upvotes": 46,
      "mentions": 17,
      "mention_change": -20,
      "source_url": "https://feargreedmeter.com/top-100-most-popular-meme-stocks-today",
      "raw_text": "# 6 . DTE DTE Energy 46 17 -20"
    },
    {
      "fetched_at_local": "2026-07-12T20:36:41+02:00",
      "fetched_at_utc": "2026-07-12T18:36:41+00:00",
      "rank": 7,
      "ticker": "QQQ",
      "company_name": "Invesco QQQ ETF",
      "upvotes": 209,
      "mentions": 16,
      "mention_change": -37,
      "source_url": "https://feargreedmeter.com/top-100-most-popular-meme-stocks-today",
      "raw_text": "# 7 . QQQ Invesco QQQ ETF 209 16 -37"
    },
    {
      "fetched_at_local": "2026-07-12T20:36:41+02:00",
      "fetched_at_utc": "2026-07-12T18:36:41+00:00",
      "rank": 8,
      "ticker": "HBM",
      "company_name": "Hudbay Minerals",
      "upvotes": 59,
      "mentions": 15,
      "mention_change": -5,
      "source_url": "https://feargreedmeter.com/top-100-most-popular-meme-stocks-today",
      "raw_text": "# 8 . HBM Hudbay Minerals 59 15 -5"
    },
    {
      "fetched_at_local": "2026-07-12T20:36:41+02:00",
      "fetched_at_utc": "2026-07-12T18:36:41+00:00",
      "rank": 9,
      "ticker": "VOO",
      "company_name": "Vanguard S&P 500 ETF",
      "upvotes": 71,
      "mentions": 15,
      "mention_change": -18,
      "source_url": "https://feargreedmeter.com/top-100-most-popular-meme-stocks-today",
      "raw_text": "# 9 . VOO Vanguard S&P 500 ETF 71 15 -18"
    },
    {
      "fetched_at_local": "2026-07-12T20:36:41+02:00",
      "fetched_at_utc": "2026-07-12T18:36:41+00:00",
      "rank": 10,
      "ticker": "RKLB",
      "company_name": "Rocket Lab USA",
      "upvotes": 155,
      "mentions": 12,
      "mention_change": -8,
      "source_url": "https://feargreedmeter.com/top-100-most-popular-meme-stocks-today",
      "raw_text": "# 10 . RKLB Rocket Lab USA 155 12 -8"
    },
    {
      "fetched_at_local": "2026-07-12T20:36:41+02:00",
      "fetched_at_utc": "2026-07-12T18:36:41+00:00",
      "rank": 11,
      "ticker": "META",
      "company_name": "Meta Platforms (Facebook)",
      "upvotes": 80,
      "mentions": 12,
      "mention_change": -44,
      "source_url": "https://feargreedmeter.com/top-100-most-popular-meme-stocks-today",
      "raw_text": "# 11 . META Meta Platforms (Facebook) 80 12 -44"
    },
    {
      "fetched_at_local": "2026-07-12T20:36:41+02:00",
      "fetched_at_utc": "2026-07-12T18:36:41+00:00",
      "rank": 12,
      "ticker": "AAPL",
      "company_name": "Apple",
      "upvotes": 27,
      "mentions": 11,
      "mention_change": -12,
      "source_url": "https://feargreedmeter.com/top-100-most-popular-meme-stocks-today",
      "raw_text": "# 12 . AAPL Apple 27 11 -12"
    },
    {
      "fetched_at_local": "2026-07-12T20:36:41+02:00",
      "fetched_at_utc": "2026-07-12T18:36:41+00:00",
      "rank": 13,
      "ticker": "AMD",
      "company_name": "AMD",
      "upvotes": 40,
      "mentions": 11,
      "mention_change": -4,
      "source_url": "https://feargreedmeter.com/top-100-most-popular-meme-stocks-today",
      "raw_text": "# 13 . AMD AMD 40 11 -4"
    },
    {
      "fetched_at_local": "2026-07-12T20:36:41+02:00",
      "fetched_at_utc": "2026-07-12T18:36:41+00:00",
      "rank": 14,
      "ticker": "VTI",
      "company_name": "Vanguard Total Stock Market ETF",
      "upvotes": 88,
      "mentions": 11,
      "mention_change": -5,
      "source_url": "https://feargreedmeter.com/top-100-most-popular-meme-stocks-today",
      "raw_text": "# 14 . VTI Vanguard Total Stock Market ETF 88 11 -5"
    },
    {
      "fetched_at_local": "2026-07-12T20:36:41+02:00",
      "fetched_at_utc": "2026-07-12T18:36:41+00:00",
      "rank": 15,
      "ticker": "IP",
      "company_name": "International Paper",
      "upvotes": 56,
      "mentions": 10,
      "mention_change": -29,
      "source_url": "https://feargreedmeter.com/top-100-most-popular-meme-stocks-today",
      "raw_text": "# 15 . IP International Paper 56 10 -29"
    },
    {
      "fetched_at_local": "2026-07-12T20:36:41+02:00",
      "fetched_at_utc": "2026-07-12T18:36:41+00:00",
      "rank": 16,
      "ticker": "IBKR",
      "company_name": "Interactive Brokers",
      "upvotes": 37,
      "mentions": 9,
      "mention_change": 5,
      "source_url": "https://feargreedmeter.com/top-100-most-popular-meme-stocks-today",
      "raw_text": "# 16 . IBKR Interactive Brokers 37 9 + 5"
    },
    {
      "fetched_at_local": "2026-07-12T20:36:41+02:00",
      "fetched_at_utc": "2026-07-12T18:36:41+00:00",
      "rank": 17,
      "ticker": "BE",
      "company_name": "Bloom Energy",
      "upvotes": 39,
      "mentions": 9,
      "mention_change": -2,
      "source_url": "https://feargreedmeter.com/top-100-most-popular-meme-stocks-today",
      "raw_text": "# 17 . BE Bloom Energy 39 9 -2"
    },
    {
      "fetched_at_local": "2026-07-12T20:36:41+02:00",
      "fetched_at_utc": "2026-07-12T18:36:41+00:00",
      "rank": 18,
      "ticker": "FCF",
      "company_name": "First Commonwealth Financial Corp",
      "upvotes": 13,
      "mentions": 9,
      "mention_change": 3,
      "source_url": "https://feargreedmeter.com/top-100-most-popular-meme-stocks-today",
      "raw_text": "# 18 . FCF First Commonwealth Financial Corp 13 9 + 3"
    },
    {
      "fetched_at_local": "2026-07-12T20:36:41+02:00",
      "fetched_at_utc": "2026-07-12T18:36:41+00:00",
      "rank": 19,
      "ticker": "AM",
      "company_name": "Antero Midstream",
      "upvotes": 1181,
      "mentions": 8,
      "mention_change": -2,
      "source_url": "https://feargreedmeter.com/top-100-most-popular-meme-stocks-today",
      "raw_text": "# 19 . AM Antero Midstream 1,181 8 -2"
    },
    {
      "fetched_at_local": "2026-07-12T20:36:41+02:00",
      "fetched_at_utc": "2026-07-12T18:36:41+00:00",
      "rank": 20,
      "ticker": "YOU",
      "company_name": "CLEAR Secure",
      "upvotes": 29,
      "mentions": 8,
      "mention_change": 3,
      "source_url": "https://feargreedmeter.com/top-100-most-popular-meme-stocks-today",
      "raw_text": "# 20 . YOU CLEAR Secure 29 8 + 3"
    },
    {
      "fetched_at_local": "2026-07-12T20:36:41+02:00",
      "fetched_at_utc": "2026-07-12T18:36:41+00:00",
      "rank": 21,
      "ticker": "JPM",
      "company_name": "JPMorgan Chase",
      "upvotes": 29,
      "mentions": 7,
      "mention_change": 6,
      "source_url": "https://feargreedmeter.com/top-100-most-popular-meme-stocks-today",
      "raw_text": "# 21 . JPM JPMorgan Chase 29 7 + 6"
    },
    {
      "fetched_at_local": "2026-07-12T20:36:41+02:00",
      "fetched_at_utc": "2026-07-12T18:36:41+00:00",
      "rank": 22,
      "ticker": "WEN",
      "company_name": "Wendy’s Company",
      "upvotes": 10,
      "mentions": 7,
      "mention_change": -4,
      "source_url": "https://feargreedmeter.com/top-100-most-popular-meme-stocks-today",
      "raw_text": "# 22 . WEN Wendy’s Company 10 7 -4"
    },
    {
      "fetched_at_local": "2026-07-12T20:36:41+02:00",
      "fetched_at_utc": "2026-07-12T18:36:41+00:00",
      "rank": 23,
      "ticker": "BYD",
      "company_name": "Boyd Gaming",
      "upvotes": 110,
      "mentions": 7,
      "mention_change": 7,
      "source_url": "https://feargreedmeter.com/top-100-most-popular-meme-stocks-today",
      "raw_text": "# 23 . BYD Boyd Gaming 110 7 + 7"
    },
    {
      "fetched_at_local": "2026-07-12T20:36:41+02:00",
      "fetched_at_utc": "2026-07-12T18:36:41+00:00",
      "rank": 24,
      "ticker": "BB",
      "company_name": "BlackBerry",
      "upvotes": 66,
      "mentions": 7,
      "mention_change": 6,
      "source_url": "https://feargreedmeter.com/top-100-most-popular-meme-stocks-today",
      "raw_text": "# 24 . BB BlackBerry 66 7 + 6"
    },
    {
      "fetched_at_local": "2026-07-12T20:36:41+02:00",
      "fetched_at_utc": "2026-07-12T18:36:41+00:00",
      "rank": 25,
      "ticker": "ASTS",
      "company_name": "AST SpaceMobile",
      "upvotes": 6,
      "mentions": 7,
      "mention_change": -8,
      "source_url": "https://feargreedmeter.com/top-100-most-popular-meme-stocks-today",
      "raw_text": "# 25 . ASTS AST SpaceMobile 6 7 -8"
    },
    {
      "fetched_at_local": "2026-07-12T20:36:41+02:00",
      "fetched_at_utc": "2026-07-12T18:36:41+00:00",
      "rank": 26,
      "ticker": "DC",
      "company_name": "Dakota Gold",
      "upvotes": 15,
      "mentions": 7,
      "mention_change": 6,
      "source_url": "https://feargreedmeter.com/top-100-most-popular-meme-stocks-today",
      "raw_text": "# 26 . DC Dakota Gold 15 7 + 6"
    },
    {
      "fetched_at_local": "2026-07-12T20:36:41+02:00",
      "fetched_at_utc": "2026-07-12T18:36:41+00:00",
      "rank": 27,
      "ticker": "EU",
      "company_name": "enCore Energy",
      "upvotes": 30,
      "mentions": 7,
      "mention_change": -4,
      "source_url": "https://feargreedmeter.com/top-100-most-popular-meme-stocks-today",
      "raw_text": "# 27 . EU enCore Energy 30 7 -4"
    },
    {
      "fetched_at_local": "2026-07-12T20:36:41+02:00",
      "fetched_at_utc": "2026-07-12T18:36:41+00:00",
      "rank": 28,
      "ticker": "GOOG",
      "company_name": "Alphabet (Google)",
      "upvotes": 66,
      "mentions": 6,
      "mention_change": -12,
      "source_url": "https://feargreedmeter.com/top-100-most-popular-meme-stocks-today",
      "raw_text": "# 28 . GOOG Alphabet (Google) 66 6 -12"
    },
    {
      "fetched_at_local": "2026-07-12T20:36:41+02:00",
      "fetched_at_utc": "2026-07-12T18:36:41+00:00",
      "rank": 29,
      "ticker": "TSLA",
      "company_name": "Tesla",
      "upvotes": 9,
      "mentions": 6,
      "mention_change": -17,
      "source_url": "https://feargreedmeter.com/top-100-most-popular-meme-stocks-today",
      "raw_text": "# 29 . TSLA Tesla 9 6 -17"
    },
    {
      "fetched_at_local": "2026-07-12T20:36:41+02:00",
      "fetched_at_utc": "2026-07-12T18:36:41+00:00",
      "rank": 30,
      "ticker": "SCHD",
      "company_name": "Schwab Strategic Trust - CSIM Schwab US Dividend Equity ETF",
      "upvotes": 10,
      "mentions": 6,
      "mention_change": 3,
      "source_url": "https://feargreedmeter.com/top-100-most-popular-meme-stocks-today",
      "raw_text": "# 30 . SCHD Schwab Strategic Trust - CSIM Schwab US Dividend Equity ETF 10 6 + 3"
    },
    {
      "fetched_at_local": "2026-07-12T20:36:41+02:00",
      "fetched_at_utc": "2026-07-12T18:36:41+00:00",
      "rank": 31,
      "ticker": "LINK",
      "company_name": "Interlink Electronics",
      "upvotes": 7,
      "mentions": 6,
      "mention_change": -1,
      "source_url": "https://feargreedmeter.com/top-100-most-popular-meme-stocks-today",
      "raw_text": "# 31 . LINK Interlink Electronics 7 6 -1"
    },
    {
      "fetched_at_local": "2026-07-12T20:36:41+02:00",
      "fetched_at_utc": "2026-07-12T18:36:41+00:00",
      "rank": 32,
      "ticker": "NFLX",
      "company_name": "Netflix",
      "upvotes": 5,
      "mentions": 5,
      "mention_change": -37,
      "source_url": "https://feargreedmeter.com/top-100-most-popular-meme-stocks-today",
      "raw_text": "# 32 . NFLX Netflix 5 5 -37"
    },
    {
      "fetched_at_local": "2026-07-12T20:36:41+02:00",
      "fetched_at_utc": "2026-07-12T18:36:41+00:00",
      "rank": 33,
      "ticker": "CC",
      "company_name": "Chemours",
      "upvotes": 8,
      "mentions": 5,
      "mention_change": -7,
      "source_url": "https://feargreedmeter.com/top-100-most-popular-meme-stocks-today",
      "raw_text": "# 33 . CC Chemours 8 5 -7"
    },
    {
      "fetched_at_local": "2026-07-12T20:36:41+02:00",
      "fetched_at_utc": "2026-07-12T18:36:41+00:00",
      "rank": 34,
      "ticker": "VT",
      "company_name": "Vanguard Group, Inc. - Vanguard Total World Stock ETF",
      "upvotes": 36,
      "mentions": 5,
      "mention_change": -1,
      "source_url": "https://feargreedmeter.com/top-100-most-popular-meme-stocks-today",
      "raw_text": "# 34 . VT Vanguard Group, Inc. - Vanguard Total World Stock ETF 36 5 -1"
    },
    {
      "fetched_at_local": "2026-07-12T20:36:41+02:00",
      "fetched_at_utc": "2026-07-12T18:36:41+00:00",
      "rank": 35,
      "ticker": "SGOV",
      "company_name": "iShares Trust - iShares 0-3 Month Treasury Bond ETF",
      "upvotes": 16,
      "mentions": 5,
      "mention_change": -1,
      "source_url": "https://feargreedmeter.com/top-100-most-popular-meme-stocks-today",
      "raw_text": "# 35 . SGOV iShares Trust - iShares 0-3 Month Treasury Bond ETF 16 5 -1"
    },
    {
      "fetched_at_local": "2026-07-12T20:36:41+02:00",
      "fetched_at_utc": "2026-07-12T18:36:41+00:00",
      "rank": 36,
      "ticker": "FOR",
      "company_name": "Forestar Group",
      "upvotes": 22,
      "mentions": 5,
      "mention_change": 4,
      "source_url": "https://feargreedmeter.com/top-100-most-popular-meme-stocks-today",
      "raw_text": "# 36 . FOR Forestar Group 22 5 + 4"
    },
    {
      "fetched_at_local": "2026-07-12T20:36:41+02:00",
      "fetched_at_utc": "2026-07-12T18:36:41+00:00",
      "rank": 37,
      "ticker": "ONDS",
      "company_name": "Ondas Holdings",
      "upvotes": 8,
      "mentions": 5,
      "mention_change": -5,
      "source_url": "https://feargreedmeter.com/top-100-most-popular-meme-stocks-today",
      "raw_text": "# 37 . ONDS Ondas Holdings 8 5 -5"
    },
    {
      "fetched_at_local": "2026-07-12T20:36:41+02:00",
      "fetched_at_utc": "2026-07-12T18:36:41+00:00",
      "rank": 38,
      "ticker": "LMT",
      "company_name": "Lockheed Martin",
      "upvotes": 12,
      "mentions": 4,
      "mention_change": -3,
      "source_url": "https://feargreedmeter.com/top-100-most-popular-meme-stocks-today",
      "raw_text": "# 38 . LMT Lockheed Martin 12 4 -3"
    },
    {
      "fetched_at_local": "2026-07-12T20:36:41+02:00",
      "fetched_at_utc": "2026-07-12T18:36:41+00:00",
      "rank": 39,
      "ticker": "ES",
      "company_name": "Eversource Energy",
      "upvotes": 6,
      "mentions": 4,
      "mention_change": -12,
      "source_url": "https://feargreedmeter.com/top-100-most-popular-meme-stocks-today",
      "raw_text": "# 39 . ES Eversource Energy 6 4 -12"
    },
    {
      "fetched_at_local": "2026-07-12T20:36:41+02:00",
      "fetched_at_utc": "2026-07-12T18:36:41+00:00",
      "rank": 40,
      "ticker": "NOW",
      "company_name": "ServiceNow",
      "upvotes": 9,
      "mentions": 4,
      "mention_change": -2,
      "source_url": "https://feargreedmeter.com/top-100-most-popular-meme-stocks-today",
      "raw_text": "# 40 . NOW ServiceNow 9 4 -2"
    },
    {
      "fetched_at_local": "2026-07-12T20:36:41+02:00",
      "fetched_at_utc": "2026-07-12T18:36:41+00:00",
      "rank": 41,
      "ticker": "IT",
      "company_name": "Gartner",
      "upvotes": 537,
      "mentions": 4,
      "mention_change": -9,
      "source_url": "https://feargreedmeter.com/top-100-most-popular-meme-stocks-today",
      "raw_text": "# 41 . IT Gartner 537 4 -9"
    },
    {
      "fetched_at_local": "2026-07-12T20:36:41+02:00",
      "fetched_at_utc": "2026-07-12T18:36:41+00:00",
      "rank": 42,
      "ticker": "OR",
      "company_name": "Osisko Gold Royalties",
      "upvotes": 20,
      "mentions": 4,
      "mention_change": 1,
      "source_url": "https://feargreedmeter.com/top-100-most-popular-meme-stocks-today",
      "raw_text": "# 42 . OR Osisko Gold Royalties 20 4 + 1"
    },
    {
      "fetched_at_local": "2026-07-12T20:36:41+02:00",
      "fetched_at_utc": "2026-07-12T18:36:41+00:00",
      "rank": 43,
      "ticker": "ET",
      "company_name": "Energy Transfer Partners",
      "upvotes": 22,
      "mentions": 4,
      "mention_change": 3,
      "source_url": "https://feargreedmeter.com/top-100-most-popular-meme-stocks-today",
      "raw_text": "# 43 . ET Energy Transfer Partners 22 4 + 3"
    },
    {
      "fetched_at_local": "2026-07-12T20:36:41+02:00",
      "fetched_at_utc": "2026-07-12T18:36:41+00:00",
      "rank": 44,
      "ticker": "SOXX",
      "company_name": "BlackRock Institutional Trust Company N.A. - BTC iShares PHLX Semicond",
      "upvotes": 118,
      "mentions": 4,
      "mention_change": 2,
      "source_url": "https://feargreedmeter.com/top-100-most-popular-meme-stocks-today",
      "raw_text": "# 44 . SOXX BlackRock Institutional Trust Company N.A. - BTC iShares PHLX Semicond 118 4 + 2"
    },
    {
      "fetched_at_local": "2026-07-12T20:36:41+02:00",
      "fetched_at_utc": "2026-07-12T18:36:41+00:00",
      "rank": 45,
      "ticker": "VXUS",
      "company_name": "Vanguard Group, Inc. - Vanguard Total International Stock ETF",
      "upvotes": 9,
      "mentions": 4,
      "mention_change": 2,
      "source_url": "https://feargreedmeter.com/top-100-most-popular-meme-stocks-today",
      "raw_text": "# 45 . VXUS Vanguard Group, Inc. - Vanguard Total International Stock ETF 9 4 + 2"
    },
    {
      "fetched_at_local": "2026-07-12T20:36:41+02:00",
      "fetched_at_utc": "2026-07-12T18:36:41+00:00",
      "rank": 46,
      "ticker": "VIG",
      "company_name": "Vanguard Group, Inc. - Vanguard Dividend Appreciation FTF",
      "upvotes": 11,
      "mentions": 4,
      "mention_change": 4,
      "source_url": "https://feargreedmeter.com/top-100-most-popular-meme-stocks-today",
      "raw_text": "# 46 . VIG Vanguard Group, Inc. - Vanguard Dividend Appreciation FTF 11 4 + 4"
    },
    {
      "fetched_at_local": "2026-07-12T20:36:41+02:00",
      "fetched_at_utc": "2026-07-12T18:36:41+00:00",
      "rank": 47,
      "ticker": "LOT",
      "company_name": "Lotus Technology",
      "upvotes": 10,
      "mentions": 4,
      "mention_change": -1,
      "source_url": "https://feargreedmeter.com/top-100-most-popular-meme-stocks-today",
      "raw_text": "# 47 . LOT Lotus Technology 10 4 -1"
    },
    {
      "fetched_at_local": "2026-07-12T20:36:41+02:00",
      "fetched_at_utc": "2026-07-12T18:36:41+00:00",
      "rank": 48,
      "ticker": "DJT",
      "company_name": "Trump Media & Technology Group",
      "upvotes": 109,
      "mentions": 4,
      "mention_change": 2,
      "source_url": "https://feargreedmeter.com/top-100-most-popular-meme-stocks-today",
      "raw_text": "# 48 . DJT Trump Media & Technology Group 109 4 + 2"
    },
    {
      "fetched_at_local": "2026-07-12T20:36:41+02:00",
      "fetched_at_utc": "2026-07-12T18:36:41+00:00",
      "rank": 49,
      "ticker": "SNDK",
      "company_name": "Sandisk",
      "upvotes": 7,
      "mentions": 4,
      "mention_change": -31,
      "source_url": "https://feargreedmeter.com/top-100-most-popular-meme-stocks-today",
      "raw_text": "# 49 . SNDK Sandisk 7 4 -31"
    },
    {
      "fetched_at_local": "2026-07-12T20:36:41+02:00",
      "fetched_at_utc": "2026-07-12T18:36:41+00:00",
      "rank": 50,
      "ticker": "CRM",
      "company_name": "Salesforce",
      "upvotes": 4,
      "mentions": 3,
      "mention_change": 2,
      "source_url": "https://feargreedmeter.com/top-100-most-popular-meme-stocks-today",
      "raw_text": "# 50 . CRM Salesforce 4 3 + 2"
    },
    {
      "fetched_at_local": "2026-07-12T20:36:41+02:00",
      "fetched_at_utc": "2026-07-12T18:36:41+00:00",
      "rank": 51,
      "ticker": "ASML",
      "company_name": "ASML",
      "upvotes": 6,
      "mentions": 3,
      "mention_change": -12,
      "source_url": "https://feargreedmeter.com/top-100-most-popular-meme-stocks-today",
      "raw_text": "# 51 . ASML ASML 6 3 -12"
    },
    {
      "fetched_at_local": "2026-07-12T20:36:41+02:00",
      "fetched_at_utc": "2026-07-12T18:36:41+00:00",
      "rank": 52,
      "ticker": "VC",
      "company_name": "Visteon",
      "upvotes": 25,
      "mentions": 3,
      "mention_change": 1,
      "source_url": "https://feargreedmeter.com/top-100-most-popular-meme-stocks-today",
      "raw_text": "# 52 . VC Visteon 25 3 + 1"
    },
    {
      "fetched_at_local": "2026-07-12T20:36:41+02:00",
      "fetched_at_utc": "2026-07-12T18:36:41+00:00",
      "rank": 53,
      "ticker": "WTI",
      "company_name": "W&T Offshore",
      "upvotes": 17,
      "mentions": 3,
      "mention_change": -2,
      "source_url": "https://feargreedmeter.com/top-100-most-popular-meme-stocks-today",
      "raw_text": "# 53 . WTI W&T Offshore 17 3 -2"
    },
    {
      "fetched_at_local": "2026-07-12T20:36:41+02:00",
      "fetched_at_utc": "2026-07-12T18:36:41+00:00",
      "rank": 54,
      "ticker": "LNG",
      "company_name": "Cheniere Energy",
      "upvotes": 7,
      "mentions": 3,
      "mention_change": 2,
      "source_url": "https://feargreedmeter.com/top-100-most-popular-meme-stocks-today",
      "raw_text": "# 54 . LNG Cheniere Energy 7 3 + 2"
    },
    {
      "fetched_at_local": "2026-07-12T20:36:41+02:00",
      "fetched_at_utc": "2026-07-12T18:36:41+00:00",
      "rank": 55,
      "ticker": "SNAP",
      "company_name": "Snap",
      "upvotes": -1,
      "mentions": 3,
      "mention_change": 3,
      "source_url": "https://feargreedmeter.com/top-100-most-popular-meme-stocks-today",
      "raw_text": "# 55 . SNAP Snap -1 3 + 3"
    },
    {
      "fetched_at_local": "2026-07-12T20:36:41+02:00",
      "fetched_at_utc": "2026-07-12T18:36:41+00:00",
      "rank": 56,
      "ticker": "AGI",
      "company_name": "Alamos Gold",
      "upvotes": 5,
      "mentions": 3,
      "mention_change": -4,
      "source_url": "https://feargreedmeter.com/top-100-most-popular-meme-stocks-today",
      "raw_text": "# 56 . AGI Alamos Gold 5 3 -4"
    },
    {
      "fetched_at_local": "2026-07-12T20:36:41+02:00",
      "fetched_at_utc": "2026-07-12T18:36:41+00:00",
      "rank": 57,
      "ticker": "USO",
      "company_name": "United States Commodity Funds LLC - United States Oil Fund",
      "upvotes": 11,
      "mentions": 3,
      "mention_change": -1,
      "source_url": "https://feargreedmeter.com/top-100-most-popular-meme-stocks-today",
      "raw_text": "# 57 . USO United States Commodity Funds LLC - United States Oil Fund 11 3 -1"
    },
    {
      "fetched_at_local": "2026-07-12T20:36:41+02:00",
      "fetched_at_utc": "2026-07-12T18:36:41+00:00",
      "rank": 58,
      "ticker": "DRIP",
      "company_name": "Direxion Shares ETF Trust - Direxion Daily S&P Oil & Gas Exp. & Prod.",
      "upvotes": 5,
      "mentions": 3,
      "mention_change": 0,
      "source_url": "https://feargreedmeter.com/top-100-most-popular-meme-stocks-today",
      "raw_text": "# 58 . DRIP Direxion Shares ETF Trust - Direxion Daily S&P Oil & Gas Exp. & Prod. 5 3 + 0"
    },
    {
      "fetched_at_local": "2026-07-12T20:36:41+02:00",
      "fetched_at_utc": "2026-07-12T18:36:41+00:00",
      "rank": 59,
      "ticker": "UAE",
      "company_name": "BlackRock Institutional Trust Company N.A. - iShares MSCI UAE ETF",
      "upvotes": 31,
      "mentions": 3,
      "mention_change": 2,
      "source_url": "https://feargreedmeter.com/top-100-most-popular-meme-stocks-today",
      "raw_text": "# 59 . UAE BlackRock Institutional Trust Company N.A. - iShares MSCI UAE ETF 31 3 + 2"
    },
    {
      "fetched_at_local": "2026-07-12T20:36:41+02:00",
      "fetched_at_utc": "2026-07-12T18:36:41+00:00",
      "rank": 60,
      "ticker": "ESG",
      "company_name": "FlexShares Trust - FlexShares STOXX US ESG Impact Index Fund",
      "upvotes": null,
      "mentions": 3,
      "mention_change": 2,
      "source_url": "https://feargreedmeter.com/top-100-most-popular-meme-stocks-today",
      "raw_text": "# 60 . ESG FlexShares Trust - FlexShares STOXX US ESG Impact Index Fund 3 + 2"
    },
    {
      "fetched_at_local": "2026-07-12T20:36:41+02:00",
      "fetched_at_utc": "2026-07-12T18:36:41+00:00",
      "rank": 61,
      "ticker": "VNQ",
      "company_name": "Vanguard Group, Inc. - Vanguard Real Estate Index Fund ETF",
      "upvotes": 4,
      "mentions": 3,
      "mention_change": 3,
      "source_url": "https://feargreedmeter.com/top-100-most-popular-meme-stocks-today",
      "raw_text": "# 61 . VNQ Vanguard Group, Inc. - Vanguard Real Estate Index Fund ETF 4 3 + 3"
    },
    {
      "fetched_at_local": "2026-07-12T20:36:41+02:00",
      "fetched_at_utc": "2026-07-12T18:36:41+00:00",
      "rank": 62,
      "ticker": "NU",
      "company_name": "Nu Holdings",
      "upvotes": 2,
      "mentions": 3,
      "mention_change": 2,
      "source_url": "https://feargreedmeter.com/top-100-most-popular-meme-stocks-today",
      "raw_text": "# 62 . NU Nu Holdings 2 3 + 2"
    },
    {
      "fetched_at_local": "2026-07-12T20:36:41+02:00",
      "fetched_at_utc": "2026-07-12T18:36:41+00:00",
      "rank": 63,
      "ticker": "CD",
      "company_name": "Chindata",
      "upvotes": -2,
      "mentions": 3,
      "mention_change": -3,
      "source_url": "https://feargreedmeter.com/top-100-most-popular-meme-stocks-today",
      "raw_text": "# 63 . CD Chindata -2 3 -3"
    },
    {
      "fetched_at_local": "2026-07-12T20:36:41+02:00",
      "fetched_at_utc": "2026-07-12T18:36:41+00:00",
      "rank": 64,
      "ticker": "RR",
      "company_name": "Richtech Robotics",
      "upvotes": 5,
      "mentions": 3,
      "mention_change": -3,
      "source_url": "https://feargreedmeter.com/top-100-most-popular-meme-stocks-today",
      "raw_text": "# 64 . RR Richtech Robotics 5 3 -3"
    },
    {
      "fetched_at_local": "2026-07-12T20:36:41+02:00",
      "fetched_at_utc": "2026-07-12T18:36:41+00:00",
      "rank": 65,
      "ticker": "WAY",
      "company_name": "Waystar",
      "upvotes": 9,
      "mentions": 3,
      "mention_change": 2,
      "source_url": "https://feargreedmeter.com/top-100-most-popular-meme-stocks-today",
      "raw_text": "# 65 . WAY Waystar 9 3 + 2"
    },
    {
      "fetched_at_local": "2026-07-12T20:36:41+02:00",
      "fetched_at_utc": "2026-07-12T18:36:41+00:00",
      "rank": 66,
      "ticker": "OS",
      "company_name": "OneStream",
      "upvotes": 72,
      "mentions": 3,
      "mention_change": -2,
      "source_url": "https://feargreedmeter.com/top-100-most-popular-meme-stocks-today",
      "raw_text": "# 66 . OS OneStream 72 3 -2"
    },
    {
      "fetched_at_local": "2026-07-12T20:36:41+02:00",
      "fetched_at_utc": "2026-07-12T18:36:41+00:00",
      "rank": 67,
      "ticker": "AMZN",
      "company_name": "Amazon",
      "upvotes": 12,
      "mentions": 2,
      "mention_change": -8,
      "source_url": "https://feargreedmeter.com/top-100-most-popular-meme-stocks-today",
      "raw_text": "# 67 . AMZN Amazon 12 2 -8"
    },
    {
      "fetched_at_local": "2026-07-12T20:36:41+02:00",
      "fetched_at_utc": "2026-07-12T18:36:41+00:00",
      "rank": 68,
      "ticker": "INTC",
      "company_name": "Intel",
      "upvotes": -1,
      "mentions": 2,
      "mention_change": -3,
      "source_url": "https://feargreedmeter.com/top-100-most-popular-meme-stocks-today",
      "raw_text": "# 68 . INTC Intel -1 2 -3"
    },
    {
      "fetched_at_local": "2026-07-12T20:36:41+02:00",
      "fetched_at_utc": "2026-07-12T18:36:41+00:00",
      "rank": 69,
      "ticker": "DIS",
      "company_name": "Walt Disney",
      "upvotes": 6,
      "mentions": 2,
      "mention_change": 1,
      "source_url": "https://feargreedmeter.com/top-100-most-popular-meme-stocks-today",
      "raw_text": "# 69 . DIS Walt Disney 6 2 + 1"
    },
    {
      "fetched_at_local": "2026-07-12T20:36:41+02:00",
      "fetched_at_utc": "2026-07-12T18:36:41+00:00",
      "rank": 70,
      "ticker": "ORCL",
      "company_name": "Oracle",
      "upvotes": 15,
      "mentions": 2,
      "mention_change": -9,
      "source_url": "https://feargreedmeter.com/top-100-most-popular-meme-stocks-today",
      "raw_text": "# 70 . ORCL Oracle 15 2 -9"
    },
    {
      "fetched_at_local": "2026-07-12T20:36:41+02:00",
      "fetched_at_utc": "2026-07-12T18:36:41+00:00",
      "rank": 71,
      "ticker": "MCD",
      "company_name": "McDonald",
      "upvotes": 12,
      "mentions": 2,
      "mention_change": 2,
      "source_url": "https://feargreedmeter.com/top-100-most-popular-meme-stocks-today",
      "raw_text": "# 71 . MCD McDonald 12 2 + 2"
    },
    {
      "fetched_at_local": "2026-07-12T20:36:41+02:00",
      "fetched_at_utc": "2026-07-12T18:36:41+00:00",
      "rank": 72,
      "ticker": "ALL",
      "company_name": "Allstate",
      "upvotes": 3,
      "mentions": 2,
      "mention_change": -5,
      "source_url": "https://feargreedmeter.com/top-100-most-popular-meme-stocks-today",
      "raw_text": "# 72 . ALL Allstate 3 2 -5"
    },
    {
      "fetched_at_local": "2026-07-12T20:36:41+02:00",
      "fetched_at_utc": "2026-07-12T18:36:41+00:00",
      "rank": 73,
      "ticker": "GLW",
      "company_name": "Corning",
      "upvotes": 4,
      "mentions": 2,
      "mention_change": 0,
      "source_url": "https://feargreedmeter.com/top-100-most-popular-meme-stocks-today",
      "raw_text": "# 73 . GLW Corning 4 2 + 0"
    },
    {
      "fetched_at_local": "2026-07-12T20:36:41+02:00",
      "fetched_at_utc": "2026-07-12T18:36:41+00:00",
      "rank": 74,
      "ticker": "NKE",
      "company_name": "Nike",
      "upvotes": -5,
      "mentions": 2,
      "mention_change": 1,
      "source_url": "https://feargreedmeter.com/top-100-most-popular-meme-stocks-today",
      "raw_text": "# 74 . NKE Nike -5 2 + 1"
    },
    {
      "fetched_at_local": "2026-07-12T20:36:41+02:00",
      "fetched_at_utc": "2026-07-12T18:36:41+00:00",
      "rank": 75,
      "ticker": "SO",
      "company_name": "Southern Company",
      "upvotes": 13,
      "mentions": 2,
      "mention_change": 1,
      "source_url": "https://feargreedmeter.com/top-100-most-popular-meme-stocks-today",
      "raw_text": "# 75 . SO Southern Company 13 2 + 1"
    },
    {
      "fetched_at_local": "2026-07-12T20:36:41+02:00",
      "fetched_at_utc": "2026-07-12T18:36:41+00:00",
      "rank": 76,
      "ticker": "XOM",
      "company_name": "Exxon Mobil",
      "upvotes": 3,
      "mentions": 2,
      "mention_change": -2,
      "source_url": "https://feargreedmeter.com/top-100-most-popular-meme-stocks-today",
      "raw_text": "# 76 . XOM Exxon Mobil 3 2 -2"
    },
    {
      "fetched_at_local": "2026-07-12T20:36:41+02:00",
      "fetched_at_utc": "2026-07-12T18:36:41+00:00",
      "rank": 77,
      "ticker": "MS",
      "company_name": "Morgan Stanley",
      "upvotes": 9,
      "mentions": 2,
      "mention_change": 1,
      "source_url": "https://feargreedmeter.com/top-100-most-popular-meme-stocks-today",
      "raw_text": "# 77 . MS Morgan Stanley 9 2 + 1"
    },
    {
      "fetched_at_local": "2026-07-12T20:36:41+02:00",
      "fetched_at_utc": "2026-07-12T18:36:41+00:00",
      "rank": 78,
      "ticker": "USB",
      "company_name": "U.S. Bancorp",
      "upvotes": 8,
      "mentions": 2,
      "mention_change": -4,
      "source_url": "https://feargreedmeter.com/top-100-most-popular-meme-stocks-today",
      "raw_text": "# 78 . USB U.S. Bancorp 8 2 -4"
    },
    {
      "fetched_at_local": "2026-07-12T20:36:41+02:00",
      "fetched_at_utc": "2026-07-12T18:36:41+00:00",
      "rank": 79,
      "ticker": "WELL",
      "company_name": "Welltower",
      "upvotes": 9,
      "mentions": 2,
      "mention_change": 1,
      "source_url": "https://feargreedmeter.com/top-100-most-popular-meme-stocks-today",
      "raw_text": "# 79 . WELL Welltower 9 2 + 1"
    },
    {
      "fetched_at_local": "2026-07-12T20:36:41+02:00",
      "fetched_at_utc": "2026-07-12T18:36:41+00:00",
      "rank": 80,
      "ticker": "LULU",
      "company_name": "lululemon athletica",
      "upvotes": 5,
      "mentions": 2,
      "mention_change": 1,
      "source_url": "https://feargreedmeter.com/top-100-most-popular-meme-stocks-today",
      "raw_text": "# 80 . LULU lululemon athletica 5 2 + 1"
    },
    {
      "fetched_at_local": "2026-07-12T20:36:41+02:00",
      "fetched_at_utc": "2026-07-12T18:36:41+00:00",
      "rank": 81,
      "ticker": "BJ",
      "company_name": "BJ's Wholesale Club",
      "upvotes": 23,
      "mentions": 2,
      "mention_change": 1,
      "source_url": "https://feargreedmeter.com/top-100-most-popular-meme-stocks-today",
      "raw_text": "# 81 . BJ BJ's Wholesale Club 23 2 + 1"
    },
    {
      "fetched_at_local": "2026-07-12T20:36:41+02:00",
      "fetched_at_utc": "2026-07-12T18:36:41+00:00",
      "rank": 82,
      "ticker": "JD",
      "company_name": "Jingdong Mall",
      "upvotes": 18,
      "mentions": 2,
      "mention_change": 1,
      "source_url": "https://feargreedmeter.com/top-100-most-popular-meme-stocks-today",
      "raw_text": "# 82 . JD Jingdong Mall 18 2 + 1"
    },
    {
      "fetched_at_local": "2026-07-12T20:36:41+02:00",
      "fetched_at_utc": "2026-07-12T18:36:41+00:00",
      "rank": 83,
      "ticker": "PLTR",
      "company_name": "Palantir",
      "upvotes": 5,
      "mentions": 2,
      "mention_change": 1,
      "source_url": "https://feargreedmeter.com/top-100-most-popular-meme-stocks-today",
      "raw_text": "# 83 . PLTR Palantir 5 2 + 1"
    },
    {
      "fetched_at_local": "2026-07-12T20:36:41+02:00",
      "fetched_at_utc": "2026-07-12T18:36:41+00:00",
      "rank": 84,
      "ticker": "JUST",
      "company_name": "Goldman Sachs ETF Trust - Goldman Sachs Just Us Large Cap Equity ETF",
      "upvotes": 12,
      "mentions": 2,
      "mention_change": 1,
      "source_url": "https://feargreedmeter.com/top-100-most-popular-meme-stocks-today",
      "raw_text": "# 84 . JUST Goldman Sachs ETF Trust - Goldman Sachs Just Us Large Cap Equity ETF 12 2 + 1"
    },
    {
      "fetched_at_local": "2026-07-12T20:36:41+02:00",
      "fetched_at_utc": "2026-07-12T18:36:41+00:00",
      "rank": 85,
      "ticker": "SOXL",
      "company_name": "Direxion Shares ETF Trust - Direxion Daily Semiconductor Bull 3X Share",
      "upvotes": 3,
      "mentions": 2,
      "mention_change": -10,
      "source_url": "https://feargreedmeter.com/top-100-most-popular-meme-stocks-today",
      "raw_text": "# 85 . SOXL Direxion Shares ETF Trust - Direxion Daily Semiconductor Bull 3X Share 3 2 -10"
    },
    {
      "fetched_at_local": "2026-07-12T20:36:41+02:00",
      "fetched_at_utc": "2026-07-12T18:36:41+00:00",
      "rank": 86,
      "ticker": "UVXY",
      "company_name": "ProShares Trust - ProShares Ultra VIX Short-Term Futures ETF",
      "upvotes": 12,
      "mentions": 2,
      "mention_change": 2,
      "source_url": "https://feargreedmeter.com/top-100-most-popular-meme-stocks-today",
      "raw_text": "# 86 . UVXY ProShares Trust - ProShares Ultra VIX Short-Term Futures ETF 12 2 + 2"
    },
    {
      "fetched_at_local": "2026-07-12T20:36:41+02:00",
      "fetched_at_utc": "2026-07-12T18:36:41+00:00",
      "rank": 87,
      "ticker": "MSTR",
      "company_name": "MicroStrategy",
      "upvotes": 2,
      "mentions": 2,
      "mention_change": -9,
      "source_url": "https://feargreedmeter.com/top-100-most-popular-meme-stocks-today",
      "raw_text": "# 87 . MSTR MicroStrategy 2 2 -9"
    },
    {
      "fetched_at_local": "2026-07-12T20:36:41+02:00",
      "fetched_at_utc": "2026-07-12T18:36:41+00:00",
      "rank": 88,
      "ticker": "CSV",
      "company_name": "Carriage Services",
      "upvotes": 3,
      "mentions": 2,
      "mention_change": 1,
      "source_url": "https://feargreedmeter.com/top-100-most-popular-meme-stocks-today",
      "raw_text": "# 88 . CSV Carriage Services 3 2 + 1"
    },
    {
      "fetched_at_local": "2026-07-12T20:36:41+02:00",
      "fetched_at_utc": "2026-07-12T18:36:41+00:00",
      "rank": 89,
      "ticker": "PR",
      "company_name": "Permian Resources",
      "upvotes": 8,
      "mentions": 2,
      "mention_change": -2,
      "source_url": "https://feargreedmeter.com/top-100-most-popular-meme-stocks-today",
      "raw_text": "# 89 . PR Permian Resources 8 2 -2"
    },
    {
      "fetched_at_local": "2026-07-12T20:36:41+02:00",
      "fetched_at_utc": "2026-07-12T18:36:41+00:00",
      "rank": 90,
      "ticker": "LUNR",
      "company_name": "Intuitive Machines",
      "upvotes": 12,
      "mentions": 2,
      "mention_change": 0,
      "source_url": "https://feargreedmeter.com/top-100-most-popular-meme-stocks-today",
      "raw_text": "# 90 . LUNR Intuitive Machines 12 2 + 0"
    },
    {
      "fetched_at_local": "2026-07-12T20:36:41+02:00",
      "fetched_at_utc": "2026-07-12T18:36:41+00:00",
      "rank": 91,
      "ticker": "RDDT",
      "company_name": "Reddit",
      "upvotes": 12,
      "mentions": 2,
      "mention_change": -4,
      "source_url": "https://feargreedmeter.com/top-100-most-popular-meme-stocks-today",
      "raw_text": "# 91 . RDDT Reddit 12 2 -4"
    },
    {
      "fetched_at_local": "2026-07-12T20:36:41+02:00",
      "fetched_at_utc": "2026-07-12T18:36:41+00:00",
      "rank": 92,
      "ticker": "JNJ",
      "company_name": "Johnson & Johnson",
      "upvotes": 4,
      "mentions": 1,
      "mention_change": 0,
      "source_url": "https://feargreedmeter.com/top-100-most-popular-meme-stocks-today",
      "raw_text": "# 92 . JNJ Johnson & Johnson 4 1 + 0"
    },
    {
      "fetched_at_local": "2026-07-12T20:36:41+02:00",
      "fetched_at_utc": "2026-07-12T18:36:41+00:00",
      "rank": 93,
      "ticker": "WMT",
      "company_name": "Walmart",
      "upvotes": 4,
      "mentions": 1,
      "mention_change": 0,
      "source_url": "https://feargreedmeter.com/top-100-most-popular-meme-stocks-today",
      "raw_text": "# 93 . WMT Walmart 4 1 + 0"
    },
    {
      "fetched_at_local": "2026-07-12T20:36:41+02:00",
      "fetched_at_utc": "2026-07-12T18:36:41+00:00",
      "rank": 94,
      "ticker": "MA",
      "company_name": "Mastercard",
      "upvotes": 2,
      "mentions": 1,
      "mention_change": -6,
      "source_url": "https://feargreedmeter.com/top-100-most-popular-meme-stocks-today",
      "raw_text": "# 94 . MA Mastercard 2 1 -6"
    },
    {
      "fetched_at_local": "2026-07-12T20:36:41+02:00",
      "fetched_at_utc": "2026-07-12T18:36:41+00:00",
      "rank": 95,
      "ticker": "PG",
      "company_name": "Procter & Gamble",
      "upvotes": 2,
      "mentions": 1,
      "mention_change": 0,
      "source_url": "https://feargreedmeter.com/top-100-most-popular-meme-stocks-today",
      "raw_text": "# 95 . PG Procter & Gamble 2 1 + 0"
    },
    {
      "fetched_at_local": "2026-07-12T20:36:41+02:00",
      "fetched_at_utc": "2026-07-12T18:36:41+00:00",
      "rank": 96,
      "ticker": "BAC",
      "company_name": "Bank of America",
      "upvotes": 1,
      "mentions": 1,
      "mention_change": 0,
      "source_url": "https://feargreedmeter.com/top-100-most-popular-meme-stocks-today",
      "raw_text": "# 96 . BAC Bank of America 1 1 + 0"
    },
    {
      "fetched_at_local": "2026-07-12T20:36:41+02:00",
      "fetched_at_utc": "2026-07-12T18:36:41+00:00",
      "rank": 97,
      "ticker": "TSM",
      "company_name": "TSMC",
      "upvotes": 2,
      "mentions": 1,
      "mention_change": -17,
      "source_url": "https://feargreedmeter.com/top-100-most-popular-meme-stocks-today",
      "raw_text": "# 97 . TSM TSMC 2 1 -17"
    },
    {
      "fetched_at_local": "2026-07-12T20:36:41+02:00",
      "fetched_at_utc": "2026-07-12T18:36:41+00:00",
      "rank": 98,
      "ticker": "HD",
      "company_name": "Home Depot",
      "upvotes": 1,
      "mentions": 1,
      "mention_change": 0,
      "source_url": "https://feargreedmeter.com/top-100-most-popular-meme-stocks-today",
      "raw_text": "# 98 . HD Home Depot 1 1 + 0"
    },
    {
      "fetched_at_local": "2026-07-12T20:36:41+02:00",
      "fetched_at_utc": "2026-07-12T18:36:41+00:00",
      "rank": 99,
      "ticker": "KO",
      "company_name": "Coca-Cola",
      "upvotes": 4,
      "mentions": 1,
      "mention_change": -1,
      "source_url": "https://feargreedmeter.com/top-100-most-popular-meme-stocks-today",
      "raw_text": "# 99 . KO Coca-Cola 4 1 -1"
    },
    {
      "fetched_at_local": "2026-07-12T20:36:41+02:00",
      "fetched_at_utc": "2026-07-12T18:36:41+00:00",
      "rank": 100,
      "ticker": "PEP",
      "company_name": "Pepsico",
      "upvotes": 1,
      "mentions": 1,
      "mention_change": 0,
      "source_url": "https://feargreedmeter.com/top-100-most-popular-meme-stocks-today",
      "raw_text": "# 100 . PEP Pepsico 1 1 + 0"
    }
  ]
}