{
  "saved_at_utc": "2026-07-12T19:48:44+00:00",
  "source_url": "https://feargreedmeter.com/top-100-most-popular-meme-stocks-today",
  "rows_count": 100,
  "rows": [
    {
      "fetched_at_local": "2026-07-12T21:48:43+02:00",
      "fetched_at_utc": "2026-07-12T19:48:43+00:00",
      "rank": 1,
      "ticker": "SPY",
      "company_name": "SPDR S&P 500 ETF Trust",
      "upvotes": 443,
      "mentions": 70,
      "mention_change": -40,
      "source_url": "https://feargreedmeter.com/top-100-most-popular-meme-stocks-today",
      "raw_text": "# 1 . SPY SPDR S&P 500 ETF Trust 443 70 -40"
    },
    {
      "fetched_at_local": "2026-07-12T21:48:43+02:00",
      "fetched_at_utc": "2026-07-12T19:48:43+00:00",
      "rank": 2,
      "ticker": "MSFT",
      "company_name": "Microsoft",
      "upvotes": 625,
      "mentions": 51,
      "mention_change": -31,
      "source_url": "https://feargreedmeter.com/top-100-most-popular-meme-stocks-today",
      "raw_text": "# 2 . MSFT Microsoft 625 51 -31"
    },
    {
      "fetched_at_local": "2026-07-12T21:48:43+02:00",
      "fetched_at_utc": "2026-07-12T19:48:43+00:00",
      "rank": 3,
      "ticker": "SPCX",
      "company_name": "SpaceX",
      "upvotes": 1003,
      "mentions": 34,
      "mention_change": -51,
      "source_url": "https://feargreedmeter.com/top-100-most-popular-meme-stocks-today",
      "raw_text": "# 3 . SPCX SpaceX 1,003 34 -51"
    },
    {
      "fetched_at_local": "2026-07-12T21:48:43+02:00",
      "fetched_at_utc": "2026-07-12T19:48:43+00:00",
      "rank": 4,
      "ticker": "MU",
      "company_name": "Micron Technology",
      "upvotes": 106,
      "mentions": 32,
      "mention_change": -118,
      "source_url": "https://feargreedmeter.com/top-100-most-popular-meme-stocks-today",
      "raw_text": "# 4 . MU Micron Technology 106 32 -118"
    },
    {
      "fetched_at_local": "2026-07-12T21:48:43+02:00",
      "fetched_at_utc": "2026-07-12T19:48:43+00:00",
      "rank": 5,
      "ticker": "NVDA",
      "company_name": "NVIDIA",
      "upvotes": 147,
      "mentions": 24,
      "mention_change": -30,
      "source_url": "https://feargreedmeter.com/top-100-most-popular-meme-stocks-today",
      "raw_text": "# 5 . NVDA NVIDIA 147 24 -30"
    },
    {
      "fetched_at_local": "2026-07-12T21:48:43+02:00",
      "fetched_at_utc": "2026-07-12T19:48:43+00:00",
      "rank": 6,
      "ticker": "QQQ",
      "company_name": "Invesco QQQ ETF",
      "upvotes": 205,
      "mentions": 15,
      "mention_change": -32,
      "source_url": "https://feargreedmeter.com/top-100-most-popular-meme-stocks-today",
      "raw_text": "# 6 . QQQ Invesco QQQ ETF 205 15 -32"
    },
    {
      "fetched_at_local": "2026-07-12T21:48:43+02:00",
      "fetched_at_utc": "2026-07-12T19:48:43+00:00",
      "rank": 7,
      "ticker": "DTE",
      "company_name": "DTE Energy",
      "upvotes": 34,
      "mentions": 14,
      "mention_change": -18,
      "source_url": "https://feargreedmeter.com/top-100-most-popular-meme-stocks-today",
      "raw_text": "# 7 . DTE DTE Energy 34 14 -18"
    },
    {
      "fetched_at_local": "2026-07-12T21:48:43+02:00",
      "fetched_at_utc": "2026-07-12T19:48:43+00:00",
      "rank": 8,
      "ticker": "VOO",
      "company_name": "Vanguard S&P 500 ETF",
      "upvotes": 118,
      "mentions": 14,
      "mention_change": -16,
      "source_url": "https://feargreedmeter.com/top-100-most-popular-meme-stocks-today",
      "raw_text": "# 8 . VOO Vanguard S&P 500 ETF 118 14 -16"
    },
    {
      "fetched_at_local": "2026-07-12T21:48:43+02:00",
      "fetched_at_utc": "2026-07-12T19:48:43+00:00",
      "rank": 9,
      "ticker": "META",
      "company_name": "Meta Platforms (Facebook)",
      "upvotes": 100,
      "mentions": 14,
      "mention_change": -28,
      "source_url": "https://feargreedmeter.com/top-100-most-popular-meme-stocks-today",
      "raw_text": "# 9 . META Meta Platforms (Facebook) 100 14 -28"
    },
    {
      "fetched_at_local": "2026-07-12T21:48:43+02:00",
      "fetched_at_utc": "2026-07-12T19:48:43+00:00",
      "rank": 10,
      "ticker": "AAPL",
      "company_name": "Apple",
      "upvotes": 36,
      "mentions": 13,
      "mention_change": -9,
      "source_url": "https://feargreedmeter.com/top-100-most-popular-meme-stocks-today",
      "raw_text": "# 10 . AAPL Apple 36 13 -9"
    },
    {
      "fetched_at_local": "2026-07-12T21:48:43+02:00",
      "fetched_at_utc": "2026-07-12T19:48:43+00:00",
      "rank": 11,
      "ticker": "AMD",
      "company_name": "AMD",
      "upvotes": 45,
      "mentions": 13,
      "mention_change": 0,
      "source_url": "https://feargreedmeter.com/top-100-most-popular-meme-stocks-today",
      "raw_text": "# 11 . AMD AMD 45 13 + 0"
    },
    {
      "fetched_at_local": "2026-07-12T21:48:43+02:00",
      "fetched_at_utc": "2026-07-12T19:48:43+00:00",
      "rank": 12,
      "ticker": "HBM",
      "company_name": "Hudbay Minerals",
      "upvotes": 24,
      "mentions": 13,
      "mention_change": -9,
      "source_url": "https://feargreedmeter.com/top-100-most-popular-meme-stocks-today",
      "raw_text": "# 12 . HBM Hudbay Minerals 24 13 -9"
    },
    {
      "fetched_at_local": "2026-07-12T21:48:43+02:00",
      "fetched_at_utc": "2026-07-12T19:48:43+00:00",
      "rank": 13,
      "ticker": "IP",
      "company_name": "International Paper",
      "upvotes": 57,
      "mentions": 10,
      "mention_change": -28,
      "source_url": "https://feargreedmeter.com/top-100-most-popular-meme-stocks-today",
      "raw_text": "# 13 . IP International Paper 57 10 -28"
    },
    {
      "fetched_at_local": "2026-07-12T21:48:43+02:00",
      "fetched_at_utc": "2026-07-12T19:48:43+00:00",
      "rank": 14,
      "ticker": "IBKR",
      "company_name": "Interactive Brokers",
      "upvotes": 41,
      "mentions": 10,
      "mention_change": 7,
      "source_url": "https://feargreedmeter.com/top-100-most-popular-meme-stocks-today",
      "raw_text": "# 14 . IBKR Interactive Brokers 41 10 + 7"
    },
    {
      "fetched_at_local": "2026-07-12T21:48:43+02:00",
      "fetched_at_utc": "2026-07-12T19:48:43+00:00",
      "rank": 15,
      "ticker": "VTI",
      "company_name": "Vanguard Total Stock Market ETF",
      "upvotes": 134,
      "mentions": 10,
      "mention_change": -4,
      "source_url": "https://feargreedmeter.com/top-100-most-popular-meme-stocks-today",
      "raw_text": "# 15 . VTI Vanguard Total Stock Market ETF 134 10 -4"
    },
    {
      "fetched_at_local": "2026-07-12T21:48:43+02:00",
      "fetched_at_utc": "2026-07-12T19:48:43+00:00",
      "rank": 16,
      "ticker": "JPM",
      "company_name": "JPMorgan Chase",
      "upvotes": 30,
      "mentions": 9,
      "mention_change": 8,
      "source_url": "https://feargreedmeter.com/top-100-most-popular-meme-stocks-today",
      "raw_text": "# 16 . JPM JPMorgan Chase 30 9 + 8"
    },
    {
      "fetched_at_local": "2026-07-12T21:48:43+02:00",
      "fetched_at_utc": "2026-07-12T19:48:43+00:00",
      "rank": 17,
      "ticker": "FCF",
      "company_name": "First Commonwealth Financial Corp",
      "upvotes": 14,
      "mentions": 9,
      "mention_change": 4,
      "source_url": "https://feargreedmeter.com/top-100-most-popular-meme-stocks-today",
      "raw_text": "# 17 . FCF First Commonwealth Financial Corp 14 9 + 4"
    },
    {
      "fetched_at_local": "2026-07-12T21:48:43+02:00",
      "fetched_at_utc": "2026-07-12T19:48:43+00:00",
      "rank": 18,
      "ticker": "RKLB",
      "company_name": "Rocket Lab USA",
      "upvotes": 31,
      "mentions": 9,
      "mention_change": -16,
      "source_url": "https://feargreedmeter.com/top-100-most-popular-meme-stocks-today",
      "raw_text": "# 18 . RKLB Rocket Lab USA 31 9 -16"
    },
    {
      "fetched_at_local": "2026-07-12T21:48:43+02:00",
      "fetched_at_utc": "2026-07-12T19:48:43+00:00",
      "rank": 19,
      "ticker": "BE",
      "company_name": "Bloom Energy",
      "upvotes": 34,
      "mentions": 8,
      "mention_change": -3,
      "source_url": "https://feargreedmeter.com/top-100-most-popular-meme-stocks-today",
      "raw_text": "# 19 . BE Bloom Energy 34 8 -3"
    },
    {
      "fetched_at_local": "2026-07-12T21:48:43+02:00",
      "fetched_at_utc": "2026-07-12T19:48:43+00:00",
      "rank": 20,
      "ticker": "YOU",
      "company_name": "CLEAR Secure",
      "upvotes": 29,
      "mentions": 8,
      "mention_change": 3,
      "source_url": "https://feargreedmeter.com/top-100-most-popular-meme-stocks-today",
      "raw_text": "# 20 . YOU CLEAR Secure 29 8 + 3"
    },
    {
      "fetched_at_local": "2026-07-12T21:48:43+02:00",
      "fetched_at_utc": "2026-07-12T19:48:43+00:00",
      "rank": 21,
      "ticker": "EU",
      "company_name": "enCore Energy",
      "upvotes": 32,
      "mentions": 8,
      "mention_change": -1,
      "source_url": "https://feargreedmeter.com/top-100-most-popular-meme-stocks-today",
      "raw_text": "# 21 . EU enCore Energy 32 8 -1"
    },
    {
      "fetched_at_local": "2026-07-12T21:48:43+02:00",
      "fetched_at_utc": "2026-07-12T19:48:43+00:00",
      "rank": 22,
      "ticker": "TSLA",
      "company_name": "Tesla",
      "upvotes": 17,
      "mentions": 7,
      "mention_change": -11,
      "source_url": "https://feargreedmeter.com/top-100-most-popular-meme-stocks-today",
      "raw_text": "# 22 . TSLA Tesla 17 7 -11"
    },
    {
      "fetched_at_local": "2026-07-12T21:48:43+02:00",
      "fetched_at_utc": "2026-07-12T19:48:43+00:00",
      "rank": 23,
      "ticker": "AM",
      "company_name": "Antero Midstream",
      "upvotes": 1211,
      "mentions": 7,
      "mention_change": -3,
      "source_url": "https://feargreedmeter.com/top-100-most-popular-meme-stocks-today",
      "raw_text": "# 23 . AM Antero Midstream 1,211 7 -3"
    },
    {
      "fetched_at_local": "2026-07-12T21:48:43+02:00",
      "fetched_at_utc": "2026-07-12T19:48:43+00:00",
      "rank": 24,
      "ticker": "ASTS",
      "company_name": "AST SpaceMobile",
      "upvotes": 14,
      "mentions": 7,
      "mention_change": -10,
      "source_url": "https://feargreedmeter.com/top-100-most-popular-meme-stocks-today",
      "raw_text": "# 24 . ASTS AST SpaceMobile 14 7 -10"
    },
    {
      "fetched_at_local": "2026-07-12T21:48:43+02:00",
      "fetched_at_utc": "2026-07-12T19:48:43+00:00",
      "rank": 25,
      "ticker": "DC",
      "company_name": "Dakota Gold",
      "upvotes": 19,
      "mentions": 7,
      "mention_change": 6,
      "source_url": "https://feargreedmeter.com/top-100-most-popular-meme-stocks-today",
      "raw_text": "# 25 . DC Dakota Gold 19 7 + 6"
    },
    {
      "fetched_at_local": "2026-07-12T21:48:43+02:00",
      "fetched_at_utc": "2026-07-12T19:48:43+00:00",
      "rank": 26,
      "ticker": "GOOG",
      "company_name": "Alphabet (Google)",
      "upvotes": 75,
      "mentions": 6,
      "mention_change": -12,
      "source_url": "https://feargreedmeter.com/top-100-most-popular-meme-stocks-today",
      "raw_text": "# 26 . GOOG Alphabet (Google) 75 6 -12"
    },
    {
      "fetched_at_local": "2026-07-12T21:48:43+02:00",
      "fetched_at_utc": "2026-07-12T19:48:43+00:00",
      "rank": 27,
      "ticker": "NFLX",
      "company_name": "Netflix",
      "upvotes": 7,
      "mentions": 6,
      "mention_change": -33,
      "source_url": "https://feargreedmeter.com/top-100-most-popular-meme-stocks-today",
      "raw_text": "# 27 . NFLX Netflix 7 6 -33"
    },
    {
      "fetched_at_local": "2026-07-12T21:48:43+02:00",
      "fetched_at_utc": "2026-07-12T19:48:43+00:00",
      "rank": 28,
      "ticker": "WEN",
      "company_name": "Wendy’s Company",
      "upvotes": 10,
      "mentions": 6,
      "mention_change": -3,
      "source_url": "https://feargreedmeter.com/top-100-most-popular-meme-stocks-today",
      "raw_text": "# 28 . WEN Wendy’s Company 10 6 -3"
    },
    {
      "fetched_at_local": "2026-07-12T21:48:43+02:00",
      "fetched_at_utc": "2026-07-12T19:48:43+00:00",
      "rank": 29,
      "ticker": "SNAP",
      "company_name": "Snap",
      "upvotes": -1,
      "mentions": 6,
      "mention_change": 6,
      "source_url": "https://feargreedmeter.com/top-100-most-popular-meme-stocks-today",
      "raw_text": "# 29 . SNAP Snap -1 6 + 6"
    },
    {
      "fetched_at_local": "2026-07-12T21:48:43+02:00",
      "fetched_at_utc": "2026-07-12T19:48:43+00:00",
      "rank": 30,
      "ticker": "BB",
      "company_name": "BlackBerry",
      "upvotes": 35,
      "mentions": 6,
      "mention_change": 5,
      "source_url": "https://feargreedmeter.com/top-100-most-popular-meme-stocks-today",
      "raw_text": "# 30 . BB BlackBerry 35 6 + 5"
    },
    {
      "fetched_at_local": "2026-07-12T21:48:43+02:00",
      "fetched_at_utc": "2026-07-12T19:48:43+00:00",
      "rank": 31,
      "ticker": "SCHD",
      "company_name": "Schwab Strategic Trust - CSIM Schwab US Dividend Equity ETF",
      "upvotes": 10,
      "mentions": 6,
      "mention_change": 3,
      "source_url": "https://feargreedmeter.com/top-100-most-popular-meme-stocks-today",
      "raw_text": "# 31 . SCHD Schwab Strategic Trust - CSIM Schwab US Dividend Equity ETF 10 6 + 3"
    },
    {
      "fetched_at_local": "2026-07-12T21:48:43+02:00",
      "fetched_at_utc": "2026-07-12T19:48:43+00:00",
      "rank": 32,
      "ticker": "ESG",
      "company_name": "FlexShares Trust - FlexShares STOXX US ESG Impact Index Fund",
      "upvotes": 1,
      "mentions": 6,
      "mention_change": 5,
      "source_url": "https://feargreedmeter.com/top-100-most-popular-meme-stocks-today",
      "raw_text": "# 32 . ESG FlexShares Trust - FlexShares STOXX US ESG Impact Index Fund 1 6 + 5"
    },
    {
      "fetched_at_local": "2026-07-12T21:48:43+02:00",
      "fetched_at_utc": "2026-07-12T19:48:43+00:00",
      "rank": 33,
      "ticker": "LINK",
      "company_name": "Interlink Electronics",
      "upvotes": 7,
      "mentions": 6,
      "mention_change": -1,
      "source_url": "https://feargreedmeter.com/top-100-most-popular-meme-stocks-today",
      "raw_text": "# 33 . LINK Interlink Electronics 7 6 -1"
    },
    {
      "fetched_at_local": "2026-07-12T21:48:43+02:00",
      "fetched_at_utc": "2026-07-12T19:48:43+00:00",
      "rank": 34,
      "ticker": "ASML",
      "company_name": "ASML",
      "upvotes": 13,
      "mentions": 5,
      "mention_change": -10,
      "source_url": "https://feargreedmeter.com/top-100-most-popular-meme-stocks-today",
      "raw_text": "# 34 . ASML ASML 13 5 -10"
    },
    {
      "fetched_at_local": "2026-07-12T21:48:43+02:00",
      "fetched_at_utc": "2026-07-12T19:48:43+00:00",
      "rank": 35,
      "ticker": "VT",
      "company_name": "Vanguard Group, Inc. - Vanguard Total World Stock ETF",
      "upvotes": 35,
      "mentions": 5,
      "mention_change": 0,
      "source_url": "https://feargreedmeter.com/top-100-most-popular-meme-stocks-today",
      "raw_text": "# 35 . VT Vanguard Group, Inc. - Vanguard Total World Stock ETF 35 5 + 0"
    },
    {
      "fetched_at_local": "2026-07-12T21:48:43+02:00",
      "fetched_at_utc": "2026-07-12T19:48:43+00:00",
      "rank": 36,
      "ticker": "SGOV",
      "company_name": "iShares Trust - iShares 0-3 Month Treasury Bond ETF",
      "upvotes": 17,
      "mentions": 5,
      "mention_change": -1,
      "source_url": "https://feargreedmeter.com/top-100-most-popular-meme-stocks-today",
      "raw_text": "# 36 . SGOV iShares Trust - iShares 0-3 Month Treasury Bond ETF 17 5 -1"
    },
    {
      "fetched_at_local": "2026-07-12T21:48:43+02:00",
      "fetched_at_utc": "2026-07-12T19:48:43+00:00",
      "rank": 37,
      "ticker": "FOR",
      "company_name": "Forestar Group",
      "upvotes": 70,
      "mentions": 5,
      "mention_change": 4,
      "source_url": "https://feargreedmeter.com/top-100-most-popular-meme-stocks-today",
      "raw_text": "# 37 . FOR Forestar Group 70 5 + 4"
    },
    {
      "fetched_at_local": "2026-07-12T21:48:43+02:00",
      "fetched_at_utc": "2026-07-12T19:48:43+00:00",
      "rank": 38,
      "ticker": "AMZN",
      "company_name": "Amazon",
      "upvotes": 24,
      "mentions": 4,
      "mention_change": -6,
      "source_url": "https://feargreedmeter.com/top-100-most-popular-meme-stocks-today",
      "raw_text": "# 38 . AMZN Amazon 24 4 -6"
    },
    {
      "fetched_at_local": "2026-07-12T21:48:43+02:00",
      "fetched_at_utc": "2026-07-12T19:48:43+00:00",
      "rank": 39,
      "ticker": "ES",
      "company_name": "Eversource Energy",
      "upvotes": 10,
      "mentions": 4,
      "mention_change": -11,
      "source_url": "https://feargreedmeter.com/top-100-most-popular-meme-stocks-today",
      "raw_text": "# 39 . ES Eversource Energy 10 4 -11"
    },
    {
      "fetched_at_local": "2026-07-12T21:48:43+02:00",
      "fetched_at_utc": "2026-07-12T19:48:43+00:00",
      "rank": 40,
      "ticker": "IT",
      "company_name": "Gartner",
      "upvotes": 540,
      "mentions": 4,
      "mention_change": -9,
      "source_url": "https://feargreedmeter.com/top-100-most-popular-meme-stocks-today",
      "raw_text": "# 40 . IT Gartner 540 4 -9"
    },
    {
      "fetched_at_local": "2026-07-12T21:48:43+02:00",
      "fetched_at_utc": "2026-07-12T19:48:43+00:00",
      "rank": 41,
      "ticker": "CC",
      "company_name": "Chemours",
      "upvotes": 6,
      "mentions": 4,
      "mention_change": -8,
      "source_url": "https://feargreedmeter.com/top-100-most-popular-meme-stocks-today",
      "raw_text": "# 41 . CC Chemours 6 4 -8"
    },
    {
      "fetched_at_local": "2026-07-12T21:48:43+02:00",
      "fetched_at_utc": "2026-07-12T19:48:43+00:00",
      "rank": 42,
      "ticker": "ET",
      "company_name": "Energy Transfer Partners",
      "upvotes": 27,
      "mentions": 4,
      "mention_change": 3,
      "source_url": "https://feargreedmeter.com/top-100-most-popular-meme-stocks-today",
      "raw_text": "# 42 . ET Energy Transfer Partners 27 4 + 3"
    },
    {
      "fetched_at_local": "2026-07-12T21:48:43+02:00",
      "fetched_at_utc": "2026-07-12T19:48:43+00:00",
      "rank": 43,
      "ticker": "SOXX",
      "company_name": "BlackRock Institutional Trust Company N.A. - BTC iShares PHLX Semicond",
      "upvotes": 120,
      "mentions": 4,
      "mention_change": 3,
      "source_url": "https://feargreedmeter.com/top-100-most-popular-meme-stocks-today",
      "raw_text": "# 43 . SOXX BlackRock Institutional Trust Company N.A. - BTC iShares PHLX Semicond 120 4 + 3"
    },
    {
      "fetched_at_local": "2026-07-12T21:48:43+02:00",
      "fetched_at_utc": "2026-07-12T19:48:43+00:00",
      "rank": 44,
      "ticker": "VXUS",
      "company_name": "Vanguard Group, Inc. - Vanguard Total International Stock ETF",
      "upvotes": 9,
      "mentions": 4,
      "mention_change": 3,
      "source_url": "https://feargreedmeter.com/top-100-most-popular-meme-stocks-today",
      "raw_text": "# 44 . VXUS Vanguard Group, Inc. - Vanguard Total International Stock ETF 9 4 + 3"
    },
    {
      "fetched_at_local": "2026-07-12T21:48:43+02:00",
      "fetched_at_utc": "2026-07-12T19:48:43+00:00",
      "rank": 45,
      "ticker": "VIG",
      "company_name": "Vanguard Group, Inc. - Vanguard Dividend Appreciation FTF",
      "upvotes": 10,
      "mentions": 4,
      "mention_change": 4,
      "source_url": "https://feargreedmeter.com/top-100-most-popular-meme-stocks-today",
      "raw_text": "# 45 . VIG Vanguard Group, Inc. - Vanguard Dividend Appreciation FTF 10 4 + 4"
    },
    {
      "fetched_at_local": "2026-07-12T21:48:43+02:00",
      "fetched_at_utc": "2026-07-12T19:48:43+00:00",
      "rank": 46,
      "ticker": "ONDS",
      "company_name": "Ondas Holdings",
      "upvotes": 7,
      "mentions": 4,
      "mention_change": -5,
      "source_url": "https://feargreedmeter.com/top-100-most-popular-meme-stocks-today",
      "raw_text": "# 46 . ONDS Ondas Holdings 7 4 -5"
    },
    {
      "fetched_at_local": "2026-07-12T21:48:43+02:00",
      "fetched_at_utc": "2026-07-12T19:48:43+00:00",
      "rank": 47,
      "ticker": "RDDT",
      "company_name": "Reddit",
      "upvotes": 17,
      "mentions": 4,
      "mention_change": 0,
      "source_url": "https://feargreedmeter.com/top-100-most-popular-meme-stocks-today",
      "raw_text": "# 47 . RDDT Reddit 17 4 + 0"
    },
    {
      "fetched_at_local": "2026-07-12T21:48:43+02:00",
      "fetched_at_utc": "2026-07-12T19:48:43+00:00",
      "rank": 48,
      "ticker": "LOT",
      "company_name": "Lotus Technology",
      "upvotes": 8,
      "mentions": 4,
      "mention_change": -2,
      "source_url": "https://feargreedmeter.com/top-100-most-popular-meme-stocks-today",
      "raw_text": "# 48 . LOT Lotus Technology 8 4 -2"
    },
    {
      "fetched_at_local": "2026-07-12T21:48:43+02:00",
      "fetched_at_utc": "2026-07-12T19:48:43+00:00",
      "rank": 49,
      "ticker": "OS",
      "company_name": "OneStream",
      "upvotes": 74,
      "mentions": 4,
      "mention_change": -1,
      "source_url": "https://feargreedmeter.com/top-100-most-popular-meme-stocks-today",
      "raw_text": "# 49 . OS OneStream 74 4 -1"
    },
    {
      "fetched_at_local": "2026-07-12T21:48:43+02:00",
      "fetched_at_utc": "2026-07-12T19:48:43+00:00",
      "rank": 50,
      "ticker": "SNDK",
      "company_name": "Sandisk",
      "upvotes": 8,
      "mentions": 4,
      "mention_change": -28,
      "source_url": "https://feargreedmeter.com/top-100-most-popular-meme-stocks-today",
      "raw_text": "# 50 . SNDK Sandisk 8 4 -28"
    },
    {
      "fetched_at_local": "2026-07-12T21:48:43+02:00",
      "fetched_at_utc": "2026-07-12T19:48:43+00:00",
      "rank": 51,
      "ticker": "INTC",
      "company_name": "Intel",
      "upvotes": 4,
      "mentions": 3,
      "mention_change": -3,
      "source_url": "https://feargreedmeter.com/top-100-most-popular-meme-stocks-today",
      "raw_text": "# 51 . INTC Intel 4 3 -3"
    },
    {
      "fetched_at_local": "2026-07-12T21:48:43+02:00",
      "fetched_at_utc": "2026-07-12T19:48:43+00:00",
      "rank": 52,
      "ticker": "LMT",
      "company_name": "Lockheed Martin",
      "upvotes": 10,
      "mentions": 3,
      "mention_change": -3,
      "source_url": "https://feargreedmeter.com/top-100-most-popular-meme-stocks-today",
      "raw_text": "# 52 . LMT Lockheed Martin 10 3 -3"
    },
    {
      "fetched_at_local": "2026-07-12T21:48:43+02:00",
      "fetched_at_utc": "2026-07-12T19:48:43+00:00",
      "rank": 53,
      "ticker": "ALL",
      "company_name": "Allstate",
      "upvotes": 6,
      "mentions": 3,
      "mention_change": -2,
      "source_url": "https://feargreedmeter.com/top-100-most-popular-meme-stocks-today",
      "raw_text": "# 53 . ALL Allstate 6 3 -2"
    },
    {
      "fetched_at_local": "2026-07-12T21:48:43+02:00",
      "fetched_at_utc": "2026-07-12T19:48:43+00:00",
      "rank": 54,
      "ticker": "NOW",
      "company_name": "ServiceNow",
      "upvotes": 9,
      "mentions": 3,
      "mention_change": -2,
      "source_url": "https://feargreedmeter.com/top-100-most-popular-meme-stocks-today",
      "raw_text": "# 54 . NOW ServiceNow 9 3 -2"
    },
    {
      "fetched_at_local": "2026-07-12T21:48:43+02:00",
      "fetched_at_utc": "2026-07-12T19:48:43+00:00",
      "rank": 55,
      "ticker": "CRM",
      "company_name": "Salesforce",
      "upvotes": 4,
      "mentions": 3,
      "mention_change": 2,
      "source_url": "https://feargreedmeter.com/top-100-most-popular-meme-stocks-today",
      "raw_text": "# 55 . CRM Salesforce 4 3 + 2"
    },
    {
      "fetched_at_local": "2026-07-12T21:48:43+02:00",
      "fetched_at_utc": "2026-07-12T19:48:43+00:00",
      "rank": 56,
      "ticker": "VC",
      "company_name": "Visteon",
      "upvotes": 28,
      "mentions": 3,
      "mention_change": 1,
      "source_url": "https://feargreedmeter.com/top-100-most-popular-meme-stocks-today",
      "raw_text": "# 56 . VC Visteon 28 3 + 1"
    },
    {
      "fetched_at_local": "2026-07-12T21:48:43+02:00",
      "fetched_at_utc": "2026-07-12T19:48:43+00:00",
      "rank": 57,
      "ticker": "WTI",
      "company_name": "W&T Offshore",
      "upvotes": 15,
      "mentions": 3,
      "mention_change": -2,
      "source_url": "https://feargreedmeter.com/top-100-most-popular-meme-stocks-today",
      "raw_text": "# 57 . WTI W&T Offshore 15 3 -2"
    },
    {
      "fetched_at_local": "2026-07-12T21:48:43+02:00",
      "fetched_at_utc": "2026-07-12T19:48:43+00:00",
      "rank": 58,
      "ticker": "LNG",
      "company_name": "Cheniere Energy",
      "upvotes": 7,
      "mentions": 3,
      "mention_change": 2,
      "source_url": "https://feargreedmeter.com/top-100-most-popular-meme-stocks-today",
      "raw_text": "# 58 . LNG Cheniere Energy 7 3 + 2"
    },
    {
      "fetched_at_local": "2026-07-12T21:48:43+02:00",
      "fetched_at_utc": "2026-07-12T19:48:43+00:00",
      "rank": 59,
      "ticker": "OR",
      "company_name": "Osisko Gold Royalties",
      "upvotes": 24,
      "mentions": 3,
      "mention_change": 1,
      "source_url": "https://feargreedmeter.com/top-100-most-popular-meme-stocks-today",
      "raw_text": "# 59 . OR Osisko Gold Royalties 24 3 + 1"
    },
    {
      "fetched_at_local": "2026-07-12T21:48:43+02:00",
      "fetched_at_utc": "2026-07-12T19:48:43+00:00",
      "rank": 60,
      "ticker": "AGI",
      "company_name": "Alamos Gold",
      "upvotes": 4,
      "mentions": 3,
      "mention_change": -4,
      "source_url": "https://feargreedmeter.com/top-100-most-popular-meme-stocks-today",
      "raw_text": "# 60 . AGI Alamos Gold 4 3 -4"
    },
    {
      "fetched_at_local": "2026-07-12T21:48:43+02:00",
      "fetched_at_utc": "2026-07-12T19:48:43+00:00",
      "rank": 61,
      "ticker": "USO",
      "company_name": "United States Commodity Funds LLC - United States Oil Fund",
      "upvotes": 9,
      "mentions": 3,
      "mention_change": -1,
      "source_url": "https://feargreedmeter.com/top-100-most-popular-meme-stocks-today",
      "raw_text": "# 61 . USO United States Commodity Funds LLC - United States Oil Fund 9 3 -1"
    },
    {
      "fetched_at_local": "2026-07-12T21:48:43+02:00",
      "fetched_at_utc": "2026-07-12T19:48:43+00:00",
      "rank": 62,
      "ticker": "UAE",
      "company_name": "BlackRock Institutional Trust Company N.A. - iShares MSCI UAE ETF",
      "upvotes": 33,
      "mentions": 3,
      "mention_change": 2,
      "source_url": "https://feargreedmeter.com/top-100-most-popular-meme-stocks-today",
      "raw_text": "# 62 . UAE BlackRock Institutional Trust Company N.A. - iShares MSCI UAE ETF 33 3 + 2"
    },
    {
      "fetched_at_local": "2026-07-12T21:48:43+02:00",
      "fetched_at_utc": "2026-07-12T19:48:43+00:00",
      "rank": 63,
      "ticker": "VNQ",
      "company_name": "Vanguard Group, Inc. - Vanguard Real Estate Index Fund ETF",
      "upvotes": 4,
      "mentions": 3,
      "mention_change": 3,
      "source_url": "https://feargreedmeter.com/top-100-most-popular-meme-stocks-today",
      "raw_text": "# 63 . VNQ Vanguard Group, Inc. - Vanguard Real Estate Index Fund ETF 4 3 + 3"
    },
    {
      "fetched_at_local": "2026-07-12T21:48:43+02:00",
      "fetched_at_utc": "2026-07-12T19:48:43+00:00",
      "rank": 64,
      "ticker": "NU",
      "company_name": "Nu Holdings",
      "upvotes": 1,
      "mentions": 3,
      "mention_change": 2,
      "source_url": "https://feargreedmeter.com/top-100-most-popular-meme-stocks-today",
      "raw_text": "# 64 . NU Nu Holdings 1 3 + 2"
    },
    {
      "fetched_at_local": "2026-07-12T21:48:43+02:00",
      "fetched_at_utc": "2026-07-12T19:48:43+00:00",
      "rank": 65,
      "ticker": "CD",
      "company_name": "Chindata",
      "upvotes": -1,
      "mentions": 3,
      "mention_change": -3,
      "source_url": "https://feargreedmeter.com/top-100-most-popular-meme-stocks-today",
      "raw_text": "# 65 . CD Chindata -1 3 -3"
    },
    {
      "fetched_at_local": "2026-07-12T21:48:43+02:00",
      "fetched_at_utc": "2026-07-12T19:48:43+00:00",
      "rank": 66,
      "ticker": "GOOGL",
      "company_name": "Alphabet (Google)",
      "upvotes": 10,
      "mentions": 3,
      "mention_change": -7,
      "source_url": "https://feargreedmeter.com/top-100-most-popular-meme-stocks-today",
      "raw_text": "# 66 . GOOGL Alphabet (Google) 10 3 -7"
    },
    {
      "fetched_at_local": "2026-07-12T21:48:43+02:00",
      "fetched_at_utc": "2026-07-12T19:48:43+00:00",
      "rank": 67,
      "ticker": "RR",
      "company_name": "Richtech Robotics",
      "upvotes": 5,
      "mentions": 3,
      "mention_change": -1,
      "source_url": "https://feargreedmeter.com/top-100-most-popular-meme-stocks-today",
      "raw_text": "# 67 . RR Richtech Robotics 5 3 -1"
    },
    {
      "fetched_at_local": "2026-07-12T21:48:43+02:00",
      "fetched_at_utc": "2026-07-12T19:48:43+00:00",
      "rank": 68,
      "ticker": "DJT",
      "company_name": "Trump Media & Technology Group",
      "upvotes": 101,
      "mentions": 3,
      "mention_change": 0,
      "source_url": "https://feargreedmeter.com/top-100-most-popular-meme-stocks-today",
      "raw_text": "# 68 . DJT Trump Media & Technology Group 101 3 + 0"
    },
    {
      "fetched_at_local": "2026-07-12T21:48:43+02:00",
      "fetched_at_utc": "2026-07-12T19:48:43+00:00",
      "rank": 69,
      "ticker": "WAY",
      "company_name": "Waystar",
      "upvotes": 10,
      "mentions": 3,
      "mention_change": 2,
      "source_url": "https://feargreedmeter.com/top-100-most-popular-meme-stocks-today",
      "raw_text": "# 69 . WAY Waystar 10 3 + 2"
    },
    {
      "fetched_at_local": "2026-07-12T21:48:43+02:00",
      "fetched_at_utc": "2026-07-12T19:48:43+00:00",
      "rank": 70,
      "ticker": "TSM",
      "company_name": "TSMC",
      "upvotes": 4,
      "mentions": 2,
      "mention_change": -15,
      "source_url": "https://feargreedmeter.com/top-100-most-popular-meme-stocks-today",
      "raw_text": "# 70 . TSM TSMC 4 2 -15"
    },
    {
      "fetched_at_local": "2026-07-12T21:48:43+02:00",
      "fetched_at_utc": "2026-07-12T19:48:43+00:00",
      "rank": 71,
      "ticker": "DIS",
      "company_name": "Walt Disney",
      "upvotes": 6,
      "mentions": 2,
      "mention_change": 1,
      "source_url": "https://feargreedmeter.com/top-100-most-popular-meme-stocks-today",
      "raw_text": "# 71 . DIS Walt Disney 6 2 + 1"
    },
    {
      "fetched_at_local": "2026-07-12T21:48:43+02:00",
      "fetched_at_utc": "2026-07-12T19:48:43+00:00",
      "rank": 72,
      "ticker": "ORCL",
      "company_name": "Oracle",
      "upvotes": 18,
      "mentions": 2,
      "mention_change": -7,
      "source_url": "https://feargreedmeter.com/top-100-most-popular-meme-stocks-today",
      "raw_text": "# 72 . ORCL Oracle 18 2 -7"
    },
    {
      "fetched_at_local": "2026-07-12T21:48:43+02:00",
      "fetched_at_utc": "2026-07-12T19:48:43+00:00",
      "rank": 73,
      "ticker": "MCD",
      "company_name": "McDonald",
      "upvotes": 12,
      "mentions": 2,
      "mention_change": 2,
      "source_url": "https://feargreedmeter.com/top-100-most-popular-meme-stocks-today",
      "raw_text": "# 73 . MCD McDonald 12 2 + 2"
    },
    {
      "fetched_at_local": "2026-07-12T21:48:43+02:00",
      "fetched_at_utc": "2026-07-12T19:48:43+00:00",
      "rank": 74,
      "ticker": "GLW",
      "company_name": "Corning",
      "upvotes": 4,
      "mentions": 2,
      "mention_change": -2,
      "source_url": "https://feargreedmeter.com/top-100-most-popular-meme-stocks-today",
      "raw_text": "# 74 . GLW Corning 4 2 -2"
    },
    {
      "fetched_at_local": "2026-07-12T21:48:43+02:00",
      "fetched_at_utc": "2026-07-12T19:48:43+00:00",
      "rank": 75,
      "ticker": "GL",
      "company_name": "Globe Life",
      "upvotes": 13,
      "mentions": 2,
      "mention_change": 1,
      "source_url": "https://feargreedmeter.com/top-100-most-popular-meme-stocks-today",
      "raw_text": "# 75 . GL Globe Life 13 2 + 1"
    },
    {
      "fetched_at_local": "2026-07-12T21:48:43+02:00",
      "fetched_at_utc": "2026-07-12T19:48:43+00:00",
      "rank": 76,
      "ticker": "NKE",
      "company_name": "Nike",
      "upvotes": -4,
      "mentions": 2,
      "mention_change": 1,
      "source_url": "https://feargreedmeter.com/top-100-most-popular-meme-stocks-today",
      "raw_text": "# 76 . NKE Nike -4 2 + 1"
    },
    {
      "fetched_at_local": "2026-07-12T21:48:43+02:00",
      "fetched_at_utc": "2026-07-12T19:48:43+00:00",
      "rank": 77,
      "ticker": "SO",
      "company_name": "Southern Company",
      "upvotes": 59,
      "mentions": 2,
      "mention_change": 1,
      "source_url": "https://feargreedmeter.com/top-100-most-popular-meme-stocks-today",
      "raw_text": "# 77 . SO Southern Company 59 2 + 1"
    },
    {
      "fetched_at_local": "2026-07-12T21:48:43+02:00",
      "fetched_at_utc": "2026-07-12T19:48:43+00:00",
      "rank": 78,
      "ticker": "UNH",
      "company_name": "UnitedHealth",
      "upvotes": 9,
      "mentions": 2,
      "mention_change": -7,
      "source_url": "https://feargreedmeter.com/top-100-most-popular-meme-stocks-today",
      "raw_text": "# 78 . UNH UnitedHealth 9 2 -7"
    },
    {
      "fetched_at_local": "2026-07-12T21:48:43+02:00",
      "fetched_at_utc": "2026-07-12T19:48:43+00:00",
      "rank": 79,
      "ticker": "MS",
      "company_name": "Morgan Stanley",
      "upvotes": 6,
      "mentions": 2,
      "mention_change": 1,
      "source_url": "https://feargreedmeter.com/top-100-most-popular-meme-stocks-today",
      "raw_text": "# 79 . MS Morgan Stanley 6 2 + 1"
    },
    {
      "fetched_at_local": "2026-07-12T21:48:43+02:00",
      "fetched_at_utc": "2026-07-12T19:48:43+00:00",
      "rank": 80,
      "ticker": "WELL",
      "company_name": "Welltower",
      "upvotes": 8,
      "mentions": 2,
      "mention_change": 1,
      "source_url": "https://feargreedmeter.com/top-100-most-popular-meme-stocks-today",
      "raw_text": "# 80 . WELL Welltower 8 2 + 1"
    },
    {
      "fetched_at_local": "2026-07-12T21:48:43+02:00",
      "fetched_at_utc": "2026-07-12T19:48:43+00:00",
      "rank": 81,
      "ticker": "LULU",
      "company_name": "lululemon athletica",
      "upvotes": 4,
      "mentions": 2,
      "mention_change": 1,
      "source_url": "https://feargreedmeter.com/top-100-most-popular-meme-stocks-today",
      "raw_text": "# 81 . LULU lululemon athletica 4 2 + 1"
    },
    {
      "fetched_at_local": "2026-07-12T21:48:43+02:00",
      "fetched_at_utc": "2026-07-12T19:48:43+00:00",
      "rank": 82,
      "ticker": "JD",
      "company_name": "Jingdong Mall",
      "upvotes": 18,
      "mentions": 2,
      "mention_change": 1,
      "source_url": "https://feargreedmeter.com/top-100-most-popular-meme-stocks-today",
      "raw_text": "# 82 . JD Jingdong Mall 18 2 + 1"
    },
    {
      "fetched_at_local": "2026-07-12T21:48:43+02:00",
      "fetched_at_utc": "2026-07-12T19:48:43+00:00",
      "rank": 83,
      "ticker": "PLTR",
      "company_name": "Palantir",
      "upvotes": 5,
      "mentions": 2,
      "mention_change": 0,
      "source_url": "https://feargreedmeter.com/top-100-most-popular-meme-stocks-today",
      "raw_text": "# 83 . PLTR Palantir 5 2 + 0"
    },
    {
      "fetched_at_local": "2026-07-12T21:48:43+02:00",
      "fetched_at_utc": "2026-07-12T19:48:43+00:00",
      "rank": 84,
      "ticker": "DRIP",
      "company_name": "Direxion Shares ETF Trust - Direxion Daily S&P Oil & Gas Exp. & Prod.",
      "upvotes": 4,
      "mentions": 2,
      "mention_change": -1,
      "source_url": "https://feargreedmeter.com/top-100-most-popular-meme-stocks-today",
      "raw_text": "# 84 . DRIP Direxion Shares ETF Trust - Direxion Daily S&P Oil & Gas Exp. & Prod. 4 2 -1"
    },
    {
      "fetched_at_local": "2026-07-12T21:48:43+02:00",
      "fetched_at_utc": "2026-07-12T19:48:43+00:00",
      "rank": 85,
      "ticker": "JUST",
      "company_name": "Goldman Sachs ETF Trust - Goldman Sachs Just Us Large Cap Equity ETF",
      "upvotes": 12,
      "mentions": 2,
      "mention_change": 1,
      "source_url": "https://feargreedmeter.com/top-100-most-popular-meme-stocks-today",
      "raw_text": "# 85 . JUST Goldman Sachs ETF Trust - Goldman Sachs Just Us Large Cap Equity ETF 12 2 + 1"
    },
    {
      "fetched_at_local": "2026-07-12T21:48:43+02:00",
      "fetched_at_utc": "2026-07-12T19:48:43+00:00",
      "rank": 86,
      "ticker": "SOXL",
      "company_name": "Direxion Shares ETF Trust - Direxion Daily Semiconductor Bull 3X Share",
      "upvotes": 3,
      "mentions": 2,
      "mention_change": -7,
      "source_url": "https://feargreedmeter.com/top-100-most-popular-meme-stocks-today",
      "raw_text": "# 86 . SOXL Direxion Shares ETF Trust - Direxion Daily Semiconductor Bull 3X Share 3 2 -7"
    },
    {
      "fetched_at_local": "2026-07-12T21:48:43+02:00",
      "fetched_at_utc": "2026-07-12T19:48:43+00:00",
      "rank": 87,
      "ticker": "UVXY",
      "company_name": "ProShares Trust - ProShares Ultra VIX Short-Term Futures ETF",
      "upvotes": 10,
      "mentions": 2,
      "mention_change": 2,
      "source_url": "https://feargreedmeter.com/top-100-most-popular-meme-stocks-today",
      "raw_text": "# 87 . UVXY ProShares Trust - ProShares Ultra VIX Short-Term Futures ETF 10 2 + 2"
    },
    {
      "fetched_at_local": "2026-07-12T21:48:43+02:00",
      "fetched_at_utc": "2026-07-12T19:48:43+00:00",
      "rank": 88,
      "ticker": "CSV",
      "company_name": "Carriage Services",
      "upvotes": 4,
      "mentions": 2,
      "mention_change": 1,
      "source_url": "https://feargreedmeter.com/top-100-most-popular-meme-stocks-today",
      "raw_text": "# 88 . CSV Carriage Services 4 2 + 1"
    },
    {
      "fetched_at_local": "2026-07-12T21:48:43+02:00",
      "fetched_at_utc": "2026-07-12T19:48:43+00:00",
      "rank": 89,
      "ticker": "SOFI",
      "company_name": "SoFi",
      "upvotes": 60,
      "mentions": 2,
      "mention_change": 1,
      "source_url": "https://feargreedmeter.com/top-100-most-popular-meme-stocks-today",
      "raw_text": "# 89 . SOFI SoFi 60 2 + 1"
    },
    {
      "fetched_at_local": "2026-07-12T21:48:43+02:00",
      "fetched_at_utc": "2026-07-12T19:48:43+00:00",
      "rank": 90,
      "ticker": "APLD",
      "company_name": "Applied Blockchain",
      "upvotes": 3,
      "mentions": 2,
      "mention_change": 1,
      "source_url": "https://feargreedmeter.com/top-100-most-popular-meme-stocks-today",
      "raw_text": "# 90 . APLD Applied Blockchain 3 2 + 1"
    },
    {
      "fetched_at_local": "2026-07-12T21:48:43+02:00",
      "fetched_at_utc": "2026-07-12T19:48:43+00:00",
      "rank": 91,
      "ticker": "PR",
      "company_name": "Permian Resources",
      "upvotes": 8,
      "mentions": 2,
      "mention_change": -1,
      "source_url": "https://feargreedmeter.com/top-100-most-popular-meme-stocks-today",
      "raw_text": "# 91 . PR Permian Resources 8 2 -1"
    },
    {
      "fetched_at_local": "2026-07-12T21:48:43+02:00",
      "fetched_at_utc": "2026-07-12T19:48:43+00:00",
      "rank": 92,
      "ticker": "LUNR",
      "company_name": "Intuitive Machines",
      "upvotes": 11,
      "mentions": 2,
      "mention_change": 0,
      "source_url": "https://feargreedmeter.com/top-100-most-popular-meme-stocks-today",
      "raw_text": "# 92 . LUNR Intuitive Machines 11 2 + 0"
    },
    {
      "fetched_at_local": "2026-07-12T21:48:43+02:00",
      "fetched_at_utc": "2026-07-12T19:48:43+00:00",
      "rank": 93,
      "ticker": "JNJ",
      "company_name": "Johnson & Johnson",
      "upvotes": 4,
      "mentions": 1,
      "mention_change": 0,
      "source_url": "https://feargreedmeter.com/top-100-most-popular-meme-stocks-today",
      "raw_text": "# 93 . JNJ Johnson & Johnson 4 1 + 0"
    },
    {
      "fetched_at_local": "2026-07-12T21:48:43+02:00",
      "fetched_at_utc": "2026-07-12T19:48:43+00:00",
      "rank": 94,
      "ticker": "WMT",
      "company_name": "Walmart",
      "upvotes": 4,
      "mentions": 1,
      "mention_change": 0,
      "source_url": "https://feargreedmeter.com/top-100-most-popular-meme-stocks-today",
      "raw_text": "# 94 . WMT Walmart 4 1 + 0"
    },
    {
      "fetched_at_local": "2026-07-12T21:48:43+02:00",
      "fetched_at_utc": "2026-07-12T19:48:43+00:00",
      "rank": 95,
      "ticker": "MA",
      "company_name": "Mastercard",
      "upvotes": 2,
      "mentions": 1,
      "mention_change": -6,
      "source_url": "https://feargreedmeter.com/top-100-most-popular-meme-stocks-today",
      "raw_text": "# 95 . MA Mastercard 2 1 -6"
    },
    {
      "fetched_at_local": "2026-07-12T21:48:43+02:00",
      "fetched_at_utc": "2026-07-12T19:48:43+00:00",
      "rank": 96,
      "ticker": "PG",
      "company_name": "Procter & Gamble",
      "upvotes": 2,
      "mentions": 1,
      "mention_change": 0,
      "source_url": "https://feargreedmeter.com/top-100-most-popular-meme-stocks-today",
      "raw_text": "# 96 . PG Procter & Gamble 2 1 + 0"
    },
    {
      "fetched_at_local": "2026-07-12T21:48:43+02:00",
      "fetched_at_utc": "2026-07-12T19:48:43+00:00",
      "rank": 97,
      "ticker": "BAC",
      "company_name": "Bank of America",
      "upvotes": 1,
      "mentions": 1,
      "mention_change": 0,
      "source_url": "https://feargreedmeter.com/top-100-most-popular-meme-stocks-today",
      "raw_text": "# 97 . BAC Bank of America 1 1 + 0"
    },
    {
      "fetched_at_local": "2026-07-12T21:48:43+02:00",
      "fetched_at_utc": "2026-07-12T19:48:43+00:00",
      "rank": 98,
      "ticker": "HD",
      "company_name": "Home Depot",
      "upvotes": 1,
      "mentions": 1,
      "mention_change": 0,
      "source_url": "https://feargreedmeter.com/top-100-most-popular-meme-stocks-today",
      "raw_text": "# 98 . HD Home Depot 1 1 + 0"
    },
    {
      "fetched_at_local": "2026-07-12T21:48:43+02:00",
      "fetched_at_utc": "2026-07-12T19:48:43+00:00",
      "rank": 99,
      "ticker": "KO",
      "company_name": "Coca-Cola",
      "upvotes": 3,
      "mentions": 1,
      "mention_change": -2,
      "source_url": "https://feargreedmeter.com/top-100-most-popular-meme-stocks-today",
      "raw_text": "# 99 . KO Coca-Cola 3 1 -2"
    },
    {
      "fetched_at_local": "2026-07-12T21:48:43+02:00",
      "fetched_at_utc": "2026-07-12T19:48:43+00:00",
      "rank": 100,
      "ticker": "PEP",
      "company_name": "Pepsico",
      "upvotes": 1,
      "mentions": 1,
      "mention_change": 0,
      "source_url": "https://feargreedmeter.com/top-100-most-popular-meme-stocks-today",
      "raw_text": "# 100 . PEP Pepsico 1 1 + 0"
    }
  ]
}