{
  "saved_at_utc": "2026-07-14T16:38:54+00:00",
  "source_url": "https://feargreedmeter.com/top-100-most-popular-meme-stocks-today",
  "rows_count": 100,
  "rows": [
    {
      "fetched_at_local": "2026-07-14T18:38:54+02:00",
      "fetched_at_utc": "2026-07-14T16:38:54+00:00",
      "rank": 1,
      "ticker": "IBM",
      "company_name": "IBM",
      "upvotes": 4891,
      "mentions": 743,
      "mention_change": 734,
      "source_url": "https://feargreedmeter.com/top-100-most-popular-meme-stocks-today",
      "raw_text": "# 1 . IBM IBM 4,891 743 + 734"
    },
    {
      "fetched_at_local": "2026-07-14T18:38:54+02:00",
      "fetched_at_utc": "2026-07-14T16:38:54+00:00",
      "rank": 2,
      "ticker": "SPY",
      "company_name": "SPDR S&P 500 ETF Trust",
      "upvotes": 1533,
      "mentions": 365,
      "mention_change": 97,
      "source_url": "https://feargreedmeter.com/top-100-most-popular-meme-stocks-today",
      "raw_text": "# 2 . SPY SPDR S&P 500 ETF Trust 1,533 365 + 97"
    },
    {
      "fetched_at_local": "2026-07-14T18:38:54+02:00",
      "fetched_at_utc": "2026-07-14T16:38:54+00:00",
      "rank": 3,
      "ticker": "MU",
      "company_name": "Micron Technology",
      "upvotes": 2549,
      "mentions": 330,
      "mention_change": -35,
      "source_url": "https://feargreedmeter.com/top-100-most-popular-meme-stocks-today",
      "raw_text": "# 3 . MU Micron Technology 2,549 330 -35"
    },
    {
      "fetched_at_local": "2026-07-14T18:38:54+02:00",
      "fetched_at_utc": "2026-07-14T16:38:54+00:00",
      "rank": 4,
      "ticker": "MSFT",
      "company_name": "Microsoft",
      "upvotes": 1708,
      "mentions": 261,
      "mention_change": 40,
      "source_url": "https://feargreedmeter.com/top-100-most-popular-meme-stocks-today",
      "raw_text": "# 4 . MSFT Microsoft 1,708 261 + 40"
    },
    {
      "fetched_at_local": "2026-07-14T18:38:54+02:00",
      "fetched_at_utc": "2026-07-14T16:38:54+00:00",
      "rank": 5,
      "ticker": "QQQ",
      "company_name": "Invesco QQQ ETF",
      "upvotes": 530,
      "mentions": 161,
      "mention_change": 90,
      "source_url": "https://feargreedmeter.com/top-100-most-popular-meme-stocks-today",
      "raw_text": "# 5 . QQQ Invesco QQQ ETF 530 161 + 90"
    },
    {
      "fetched_at_local": "2026-07-14T18:38:54+02:00",
      "fetched_at_utc": "2026-07-14T16:38:54+00:00",
      "rank": 6,
      "ticker": "SPCX",
      "company_name": "SpaceX",
      "upvotes": 2281,
      "mentions": 132,
      "mention_change": -65,
      "source_url": "https://feargreedmeter.com/top-100-most-popular-meme-stocks-today",
      "raw_text": "# 6 . SPCX SpaceX 2,281 132 -65"
    },
    {
      "fetched_at_local": "2026-07-14T18:38:54+02:00",
      "fetched_at_utc": "2026-07-14T16:38:54+00:00",
      "rank": 7,
      "ticker": "ORCL",
      "company_name": "Oracle",
      "upvotes": 638,
      "mentions": 124,
      "mention_change": 89,
      "source_url": "https://feargreedmeter.com/top-100-most-popular-meme-stocks-today",
      "raw_text": "# 7 . ORCL Oracle 638 124 + 89"
    },
    {
      "fetched_at_local": "2026-07-14T18:38:54+02:00",
      "fetched_at_utc": "2026-07-14T16:38:54+00:00",
      "rank": 8,
      "ticker": "NVDA",
      "company_name": "NVIDIA",
      "upvotes": 336,
      "mentions": 122,
      "mention_change": 62,
      "source_url": "https://feargreedmeter.com/top-100-most-popular-meme-stocks-today",
      "raw_text": "# 8 . NVDA NVIDIA 336 122 + 62"
    },
    {
      "fetched_at_local": "2026-07-14T18:38:54+02:00",
      "fetched_at_utc": "2026-07-14T16:38:54+00:00",
      "rank": 9,
      "ticker": "SNDK",
      "company_name": "Sandisk",
      "upvotes": 531,
      "mentions": 114,
      "mention_change": 33,
      "source_url": "https://feargreedmeter.com/top-100-most-popular-meme-stocks-today",
      "raw_text": "# 9 . SNDK Sandisk 531 114 + 33"
    },
    {
      "fetched_at_local": "2026-07-14T18:38:54+02:00",
      "fetched_at_utc": "2026-07-14T16:38:54+00:00",
      "rank": 10,
      "ticker": "ASTS",
      "company_name": "AST SpaceMobile",
      "upvotes": 490,
      "mentions": 89,
      "mention_change": 34,
      "source_url": "https://feargreedmeter.com/top-100-most-popular-meme-stocks-today",
      "raw_text": "# 10 . ASTS AST SpaceMobile 490 89 + 34"
    },
    {
      "fetched_at_local": "2026-07-14T18:38:54+02:00",
      "fetched_at_utc": "2026-07-14T16:38:54+00:00",
      "rank": 11,
      "ticker": "RKLB",
      "company_name": "Rocket Lab USA",
      "upvotes": 471,
      "mentions": 87,
      "mention_change": 26,
      "source_url": "https://feargreedmeter.com/top-100-most-popular-meme-stocks-today",
      "raw_text": "# 11 . RKLB Rocket Lab USA 471 87 + 26"
    },
    {
      "fetched_at_local": "2026-07-14T18:38:54+02:00",
      "fetched_at_utc": "2026-07-14T16:38:54+00:00",
      "rank": 12,
      "ticker": "AMD",
      "company_name": "AMD",
      "upvotes": 240,
      "mentions": 75,
      "mention_change": 50,
      "source_url": "https://feargreedmeter.com/top-100-most-popular-meme-stocks-today",
      "raw_text": "# 12 . AMD AMD 240 75 + 50"
    },
    {
      "fetched_at_local": "2026-07-14T18:38:54+02:00",
      "fetched_at_utc": "2026-07-14T16:38:54+00:00",
      "rank": 13,
      "ticker": "NBIS",
      "company_name": "Nebius Group",
      "upvotes": 227,
      "mentions": 67,
      "mention_change": 48,
      "source_url": "https://feargreedmeter.com/top-100-most-popular-meme-stocks-today",
      "raw_text": "# 13 . NBIS Nebius Group 227 67 + 48"
    },
    {
      "fetched_at_local": "2026-07-14T18:38:54+02:00",
      "fetched_at_utc": "2026-07-14T16:38:54+00:00",
      "rank": 14,
      "ticker": "USO",
      "company_name": "United States Commodity Funds LLC - United States Oil Fund",
      "upvotes": 149,
      "mentions": 62,
      "mention_change": 40,
      "source_url": "https://feargreedmeter.com/top-100-most-popular-meme-stocks-today",
      "raw_text": "# 14 . USO United States Commodity Funds LLC - United States Oil Fund 149 62 + 40"
    },
    {
      "fetched_at_local": "2026-07-14T18:38:54+02:00",
      "fetched_at_utc": "2026-07-14T16:38:54+00:00",
      "rank": 15,
      "ticker": "DTE",
      "company_name": "DTE Energy",
      "upvotes": 191,
      "mentions": 56,
      "mention_change": 12,
      "source_url": "https://feargreedmeter.com/top-100-most-popular-meme-stocks-today",
      "raw_text": "# 15 . DTE DTE Energy 191 56 + 12"
    },
    {
      "fetched_at_local": "2026-07-14T18:38:54+02:00",
      "fetched_at_utc": "2026-07-14T16:38:54+00:00",
      "rank": 16,
      "ticker": "NOW",
      "company_name": "ServiceNow",
      "upvotes": 212,
      "mentions": 55,
      "mention_change": 36,
      "source_url": "https://feargreedmeter.com/top-100-most-popular-meme-stocks-today",
      "raw_text": "# 16 . NOW ServiceNow 212 55 + 36"
    },
    {
      "fetched_at_local": "2026-07-14T18:38:54+02:00",
      "fetched_at_utc": "2026-07-14T16:38:54+00:00",
      "rank": 17,
      "ticker": "TSLA",
      "company_name": "Tesla",
      "upvotes": 93,
      "mentions": 47,
      "mention_change": 18,
      "source_url": "https://feargreedmeter.com/top-100-most-popular-meme-stocks-today",
      "raw_text": "# 17 . TSLA Tesla 93 47 + 18"
    },
    {
      "fetched_at_local": "2026-07-14T18:38:54+02:00",
      "fetched_at_utc": "2026-07-14T16:38:54+00:00",
      "rank": 18,
      "ticker": "NFLX",
      "company_name": "Netflix",
      "upvotes": 115,
      "mentions": 45,
      "mention_change": 11,
      "source_url": "https://feargreedmeter.com/top-100-most-popular-meme-stocks-today",
      "raw_text": "# 18 . NFLX Netflix 115 45 + 11"
    },
    {
      "fetched_at_local": "2026-07-14T18:38:54+02:00",
      "fetched_at_utc": "2026-07-14T16:38:54+00:00",
      "rank": 19,
      "ticker": "JPM",
      "company_name": "JPMorgan Chase",
      "upvotes": 86,
      "mentions": 41,
      "mention_change": 28,
      "source_url": "https://feargreedmeter.com/top-100-most-popular-meme-stocks-today",
      "raw_text": "# 19 . JPM JPMorgan Chase 86 41 + 28"
    },
    {
      "fetched_at_local": "2026-07-14T18:38:54+02:00",
      "fetched_at_utc": "2026-07-14T16:38:54+00:00",
      "rank": 20,
      "ticker": "PLTR",
      "company_name": "Palantir",
      "upvotes": 89,
      "mentions": 39,
      "mention_change": 32,
      "source_url": "https://feargreedmeter.com/top-100-most-popular-meme-stocks-today",
      "raw_text": "# 20 . PLTR Palantir 89 39 + 32"
    },
    {
      "fetched_at_local": "2026-07-14T18:38:54+02:00",
      "fetched_at_utc": "2026-07-14T16:38:54+00:00",
      "rank": 21,
      "ticker": "BATL",
      "company_name": "Battalion Oil",
      "upvotes": 246,
      "mentions": 36,
      "mention_change": 24,
      "source_url": "https://feargreedmeter.com/top-100-most-popular-meme-stocks-today",
      "raw_text": "# 21 . BATL Battalion Oil 246 36 + 24"
    },
    {
      "fetched_at_local": "2026-07-14T18:38:54+02:00",
      "fetched_at_utc": "2026-07-14T16:38:54+00:00",
      "rank": 22,
      "ticker": "GOOG",
      "company_name": "Alphabet (Google)",
      "upvotes": 98,
      "mentions": 36,
      "mention_change": 14,
      "source_url": "https://feargreedmeter.com/top-100-most-popular-meme-stocks-today",
      "raw_text": "# 22 . GOOG Alphabet (Google) 98 36 + 14"
    },
    {
      "fetched_at_local": "2026-07-14T18:38:54+02:00",
      "fetched_at_utc": "2026-07-14T16:38:54+00:00",
      "rank": 23,
      "ticker": "GOOGL",
      "company_name": "Alphabet (Google)",
      "upvotes": 306,
      "mentions": 34,
      "mention_change": 6,
      "source_url": "https://feargreedmeter.com/top-100-most-popular-meme-stocks-today",
      "raw_text": "# 23 . GOOGL Alphabet (Google) 306 34 + 6"
    },
    {
      "fetched_at_local": "2026-07-14T18:38:54+02:00",
      "fetched_at_utc": "2026-07-14T16:38:54+00:00",
      "rank": 24,
      "ticker": "INTC",
      "company_name": "Intel",
      "upvotes": 96,
      "mentions": 32,
      "mention_change": 19,
      "source_url": "https://feargreedmeter.com/top-100-most-popular-meme-stocks-today",
      "raw_text": "# 24 . INTC Intel 96 32 + 19"
    },
    {
      "fetched_at_local": "2026-07-14T18:38:54+02:00",
      "fetched_at_utc": "2026-07-14T16:38:54+00:00",
      "rank": 25,
      "ticker": "AM",
      "company_name": "Antero Midstream",
      "upvotes": 105,
      "mentions": 28,
      "mention_change": 14,
      "source_url": "https://feargreedmeter.com/top-100-most-popular-meme-stocks-today",
      "raw_text": "# 25 . AM Antero Midstream 105 28 + 14"
    },
    {
      "fetched_at_local": "2026-07-14T18:38:54+02:00",
      "fetched_at_utc": "2026-07-14T16:38:54+00:00",
      "rank": 26,
      "ticker": "WEN",
      "company_name": "Wendy’s Company",
      "upvotes": 155,
      "mentions": 27,
      "mention_change": 9,
      "source_url": "https://feargreedmeter.com/top-100-most-popular-meme-stocks-today",
      "raw_text": "# 26 . WEN Wendy’s Company 155 27 + 9"
    },
    {
      "fetched_at_local": "2026-07-14T18:38:54+02:00",
      "fetched_at_utc": "2026-07-14T16:38:54+00:00",
      "rank": 27,
      "ticker": "META",
      "company_name": "Meta Platforms (Facebook)",
      "upvotes": 68,
      "mentions": 26,
      "mention_change": -34,
      "source_url": "https://feargreedmeter.com/top-100-most-popular-meme-stocks-today",
      "raw_text": "# 27 . META Meta Platforms (Facebook) 68 26 -34"
    },
    {
      "fetched_at_local": "2026-07-14T18:38:54+02:00",
      "fetched_at_utc": "2026-07-14T16:38:54+00:00",
      "rank": 28,
      "ticker": "VOO",
      "company_name": "Vanguard S&P 500 ETF",
      "upvotes": 66,
      "mentions": 26,
      "mention_change": -5,
      "source_url": "https://feargreedmeter.com/top-100-most-popular-meme-stocks-today",
      "raw_text": "# 28 . VOO Vanguard S&P 500 ETF 66 26 -5"
    },
    {
      "fetched_at_local": "2026-07-14T18:38:54+02:00",
      "fetched_at_utc": "2026-07-14T16:38:54+00:00",
      "rank": 29,
      "ticker": "SOXL",
      "company_name": "Direxion Shares ETF Trust - Direxion Daily Semiconductor Bull 3X Share",
      "upvotes": 92,
      "mentions": 26,
      "mention_change": 6,
      "source_url": "https://feargreedmeter.com/top-100-most-popular-meme-stocks-today",
      "raw_text": "# 29 . SOXL Direxion Shares ETF Trust - Direxion Daily Semiconductor Bull 3X Share 92 26 + 6"
    },
    {
      "fetched_at_local": "2026-07-14T18:38:54+02:00",
      "fetched_at_utc": "2026-07-14T16:38:54+00:00",
      "rank": 30,
      "ticker": "HOOD",
      "company_name": "Robinhood",
      "upvotes": 178,
      "mentions": 24,
      "mention_change": 9,
      "source_url": "https://feargreedmeter.com/top-100-most-popular-meme-stocks-today",
      "raw_text": "# 30 . HOOD Robinhood 178 24 + 9"
    },
    {
      "fetched_at_local": "2026-07-14T18:38:54+02:00",
      "fetched_at_utc": "2026-07-14T16:38:54+00:00",
      "rank": 31,
      "ticker": "MRVL",
      "company_name": "Marvell Technology Group",
      "upvotes": 106,
      "mentions": 23,
      "mention_change": -1,
      "source_url": "https://feargreedmeter.com/top-100-most-popular-meme-stocks-today",
      "raw_text": "# 31 . MRVL Marvell Technology Group 106 23 -1"
    },
    {
      "fetched_at_local": "2026-07-14T18:38:54+02:00",
      "fetched_at_utc": "2026-07-14T16:38:54+00:00",
      "rank": 32,
      "ticker": "YOU",
      "company_name": "CLEAR Secure",
      "upvotes": 183,
      "mentions": 22,
      "mention_change": 5,
      "source_url": "https://feargreedmeter.com/top-100-most-popular-meme-stocks-today",
      "raw_text": "# 32 . YOU CLEAR Secure 183 22 + 5"
    },
    {
      "fetched_at_local": "2026-07-14T18:38:54+02:00",
      "fetched_at_utc": "2026-07-14T16:38:54+00:00",
      "rank": 33,
      "ticker": "AMZN",
      "company_name": "Amazon",
      "upvotes": 63,
      "mentions": 22,
      "mention_change": -2,
      "source_url": "https://feargreedmeter.com/top-100-most-popular-meme-stocks-today",
      "raw_text": "# 33 . AMZN Amazon 63 22 -2"
    },
    {
      "fetched_at_local": "2026-07-14T18:38:54+02:00",
      "fetched_at_utc": "2026-07-14T16:38:54+00:00",
      "rank": 34,
      "ticker": "AAPL",
      "company_name": "Apple",
      "upvotes": 44,
      "mentions": 22,
      "mention_change": -29,
      "source_url": "https://feargreedmeter.com/top-100-most-popular-meme-stocks-today",
      "raw_text": "# 34 . AAPL Apple 44 22 -29"
    },
    {
      "fetched_at_local": "2026-07-14T18:38:54+02:00",
      "fetched_at_utc": "2026-07-14T16:38:54+00:00",
      "rank": 35,
      "ticker": "OKLO",
      "company_name": "Oklo",
      "upvotes": 46,
      "mentions": 21,
      "mention_change": 12,
      "source_url": "https://feargreedmeter.com/top-100-most-popular-meme-stocks-today",
      "raw_text": "# 35 . OKLO Oklo 46 21 + 12"
    },
    {
      "fetched_at_local": "2026-07-14T18:38:54+02:00",
      "fetched_at_utc": "2026-07-14T16:38:54+00:00",
      "rank": 36,
      "ticker": "KORU",
      "company_name": "Direxion Shares ETF Trust - Direxion Daily South Korea Bull 3X Shares",
      "upvotes": 48,
      "mentions": 21,
      "mention_change": 3,
      "source_url": "https://feargreedmeter.com/top-100-most-popular-meme-stocks-today",
      "raw_text": "# 36 . KORU Direxion Shares ETF Trust - Direxion Daily South Korea Bull 3X Shares 48 21 + 3"
    },
    {
      "fetched_at_local": "2026-07-14T18:38:54+02:00",
      "fetched_at_utc": "2026-07-14T16:38:54+00:00",
      "rank": 37,
      "ticker": "HBM",
      "company_name": "Hudbay Minerals",
      "upvotes": 423,
      "mentions": 21,
      "mention_change": -12,
      "source_url": "https://feargreedmeter.com/top-100-most-popular-meme-stocks-today",
      "raw_text": "# 37 . HBM Hudbay Minerals 423 21 -12"
    },
    {
      "fetched_at_local": "2026-07-14T18:38:54+02:00",
      "fetched_at_utc": "2026-07-14T16:38:54+00:00",
      "rank": 38,
      "ticker": "ASML",
      "company_name": "ASML",
      "upvotes": 73,
      "mentions": 20,
      "mention_change": -1,
      "source_url": "https://feargreedmeter.com/top-100-most-popular-meme-stocks-today",
      "raw_text": "# 38 . ASML ASML 73 20 -1"
    },
    {
      "fetched_at_local": "2026-07-14T18:38:54+02:00",
      "fetched_at_utc": "2026-07-14T16:38:54+00:00",
      "rank": 39,
      "ticker": "RDDT",
      "company_name": "Reddit",
      "upvotes": 51,
      "mentions": 19,
      "mention_change": -2,
      "source_url": "https://feargreedmeter.com/top-100-most-popular-meme-stocks-today",
      "raw_text": "# 39 . RDDT Reddit 51 19 -2"
    },
    {
      "fetched_at_local": "2026-07-14T18:38:54+02:00",
      "fetched_at_utc": "2026-07-14T16:38:54+00:00",
      "rank": 40,
      "ticker": "CRM",
      "company_name": "Salesforce",
      "upvotes": 81,
      "mentions": 19,
      "mention_change": 9,
      "source_url": "https://feargreedmeter.com/top-100-most-popular-meme-stocks-today",
      "raw_text": "# 40 . CRM Salesforce 81 19 + 9"
    },
    {
      "fetched_at_local": "2026-07-14T18:38:54+02:00",
      "fetched_at_utc": "2026-07-14T16:38:54+00:00",
      "rank": 41,
      "ticker": "SMH",
      "company_name": "VanEck Vectors ETF Trust - VanEck Vectors Semiconductor ETF",
      "upvotes": 33,
      "mentions": 17,
      "mention_change": 12,
      "source_url": "https://feargreedmeter.com/top-100-most-popular-meme-stocks-today",
      "raw_text": "# 41 . SMH VanEck Vectors ETF Trust - VanEck Vectors Semiconductor ETF 33 17 + 12"
    },
    {
      "fetched_at_local": "2026-07-14T18:38:54+02:00",
      "fetched_at_utc": "2026-07-14T16:38:54+00:00",
      "rank": 42,
      "ticker": "FIG",
      "company_name": "Figma",
      "upvotes": 39,
      "mentions": 16,
      "mention_change": 15,
      "source_url": "https://feargreedmeter.com/top-100-most-popular-meme-stocks-today",
      "raw_text": "# 42 . FIG Figma 39 16 + 15"
    },
    {
      "fetched_at_local": "2026-07-14T18:38:54+02:00",
      "fetched_at_utc": "2026-07-14T16:38:54+00:00",
      "rank": 43,
      "ticker": "LUNR",
      "company_name": "Intuitive Machines",
      "upvotes": 145,
      "mentions": 16,
      "mention_change": 4,
      "source_url": "https://feargreedmeter.com/top-100-most-popular-meme-stocks-today",
      "raw_text": "# 43 . LUNR Intuitive Machines 145 16 + 4"
    },
    {
      "fetched_at_local": "2026-07-14T18:38:54+02:00",
      "fetched_at_utc": "2026-07-14T16:38:54+00:00",
      "rank": 44,
      "ticker": "IT",
      "company_name": "Gartner",
      "upvotes": 61,
      "mentions": 16,
      "mention_change": 2,
      "source_url": "https://feargreedmeter.com/top-100-most-popular-meme-stocks-today",
      "raw_text": "# 44 . IT Gartner 61 16 + 2"
    },
    {
      "fetched_at_local": "2026-07-14T18:38:54+02:00",
      "fetched_at_utc": "2026-07-14T16:38:54+00:00",
      "rank": 45,
      "ticker": "CC",
      "company_name": "Chemours",
      "upvotes": 40,
      "mentions": 15,
      "mention_change": 12,
      "source_url": "https://feargreedmeter.com/top-100-most-popular-meme-stocks-today",
      "raw_text": "# 45 . CC Chemours 40 15 + 12"
    },
    {
      "fetched_at_local": "2026-07-14T18:38:54+02:00",
      "fetched_at_utc": "2026-07-14T16:38:54+00:00",
      "rank": 46,
      "ticker": "ONDS",
      "company_name": "Ondas Holdings",
      "upvotes": 29,
      "mentions": 13,
      "mention_change": -2,
      "source_url": "https://feargreedmeter.com/top-100-most-popular-meme-stocks-today",
      "raw_text": "# 46 . ONDS Ondas Holdings 29 13 -2"
    },
    {
      "fetched_at_local": "2026-07-14T18:38:54+02:00",
      "fetched_at_utc": "2026-07-14T16:38:54+00:00",
      "rank": 47,
      "ticker": "SO",
      "company_name": "Southern Company",
      "upvotes": 58,
      "mentions": 13,
      "mention_change": 10,
      "source_url": "https://feargreedmeter.com/top-100-most-popular-meme-stocks-today",
      "raw_text": "# 47 . SO Southern Company 58 13 + 10"
    },
    {
      "fetched_at_local": "2026-07-14T18:38:54+02:00",
      "fetched_at_utc": "2026-07-14T16:38:54+00:00",
      "rank": 48,
      "ticker": "GS",
      "company_name": "Goldman Sachs",
      "upvotes": 23,
      "mentions": 13,
      "mention_change": 10,
      "source_url": "https://feargreedmeter.com/top-100-most-popular-meme-stocks-today",
      "raw_text": "# 48 . GS Goldman Sachs 23 13 + 10"
    },
    {
      "fetched_at_local": "2026-07-14T18:38:54+02:00",
      "fetched_at_utc": "2026-07-14T16:38:54+00:00",
      "rank": 49,
      "ticker": "CRWV",
      "company_name": "CoreWeave",
      "upvotes": 26,
      "mentions": 12,
      "mention_change": 9,
      "source_url": "https://feargreedmeter.com/top-100-most-popular-meme-stocks-today",
      "raw_text": "# 49 . CRWV CoreWeave 26 12 + 9"
    },
    {
      "fetched_at_local": "2026-07-14T18:38:54+02:00",
      "fetched_at_utc": "2026-07-14T16:38:54+00:00",
      "rank": 50,
      "ticker": "BE",
      "company_name": "Bloom Energy",
      "upvotes": 56,
      "mentions": 12,
      "mention_change": -3,
      "source_url": "https://feargreedmeter.com/top-100-most-popular-meme-stocks-today",
      "raw_text": "# 50 . BE Bloom Energy 56 12 -3"
    },
    {
      "fetched_at_local": "2026-07-14T18:38:54+02:00",
      "fetched_at_utc": "2026-07-14T16:38:54+00:00",
      "rank": 51,
      "ticker": "WTI",
      "company_name": "W&T Offshore",
      "upvotes": 38,
      "mentions": 12,
      "mention_change": 6,
      "source_url": "https://feargreedmeter.com/top-100-most-popular-meme-stocks-today",
      "raw_text": "# 51 . WTI W&T Offshore 38 12 + 6"
    },
    {
      "fetched_at_local": "2026-07-14T18:38:54+02:00",
      "fetched_at_utc": "2026-07-14T16:38:54+00:00",
      "rank": 52,
      "ticker": "ALL",
      "company_name": "Allstate",
      "upvotes": 33,
      "mentions": 12,
      "mention_change": 3,
      "source_url": "https://feargreedmeter.com/top-100-most-popular-meme-stocks-today",
      "raw_text": "# 52 . ALL Allstate 33 12 + 3"
    },
    {
      "fetched_at_local": "2026-07-14T18:38:54+02:00",
      "fetched_at_utc": "2026-07-14T16:38:54+00:00",
      "rank": 53,
      "ticker": "AVGO",
      "company_name": "Broadcom",
      "upvotes": 51,
      "mentions": 12,
      "mention_change": 6,
      "source_url": "https://feargreedmeter.com/top-100-most-popular-meme-stocks-today",
      "raw_text": "# 53 . AVGO Broadcom 51 12 + 6"
    },
    {
      "fetched_at_local": "2026-07-14T18:38:54+02:00",
      "fetched_at_utc": "2026-07-14T16:38:54+00:00",
      "rank": 54,
      "ticker": "TSM",
      "company_name": "TSMC",
      "upvotes": 34,
      "mentions": 12,
      "mention_change": -20,
      "source_url": "https://feargreedmeter.com/top-100-most-popular-meme-stocks-today",
      "raw_text": "# 54 . TSM TSMC 34 12 -20"
    },
    {
      "fetched_at_local": "2026-07-14T18:38:54+02:00",
      "fetched_at_utc": "2026-07-14T16:38:54+00:00",
      "rank": 55,
      "ticker": "EU",
      "company_name": "enCore Energy",
      "upvotes": 35,
      "mentions": 11,
      "mention_change": 1,
      "source_url": "https://feargreedmeter.com/top-100-most-popular-meme-stocks-today",
      "raw_text": "# 55 . EU enCore Energy 35 11 + 1"
    },
    {
      "fetched_at_local": "2026-07-14T18:38:54+02:00",
      "fetched_at_utc": "2026-07-14T16:38:54+00:00",
      "rank": 56,
      "ticker": "FOR",
      "company_name": "Forestar Group",
      "upvotes": 31,
      "mentions": 11,
      "mention_change": 5,
      "source_url": "https://feargreedmeter.com/top-100-most-popular-meme-stocks-today",
      "raw_text": "# 56 . FOR Forestar Group 31 11 + 5"
    },
    {
      "fetched_at_local": "2026-07-14T18:38:54+02:00",
      "fetched_at_utc": "2026-07-14T16:38:54+00:00",
      "rank": 57,
      "ticker": "OPEN",
      "company_name": "Opendoor",
      "upvotes": 77,
      "mentions": 11,
      "mention_change": -1,
      "source_url": "https://feargreedmeter.com/top-100-most-popular-meme-stocks-today",
      "raw_text": "# 57 . OPEN Opendoor 77 11 -1"
    },
    {
      "fetched_at_local": "2026-07-14T18:38:54+02:00",
      "fetched_at_utc": "2026-07-14T16:38:54+00:00",
      "rank": 58,
      "ticker": "AMC",
      "company_name": "AMC Entertainment",
      "upvotes": 14,
      "mentions": 11,
      "mention_change": 8,
      "source_url": "https://feargreedmeter.com/top-100-most-popular-meme-stocks-today",
      "raw_text": "# 58 . AMC AMC Entertainment 14 11 + 8"
    },
    {
      "fetched_at_local": "2026-07-14T18:38:54+02:00",
      "fetched_at_utc": "2026-07-14T16:38:54+00:00",
      "rank": 59,
      "ticker": "SGOV",
      "company_name": "iShares Trust - iShares 0-3 Month Treasury Bond ETF",
      "upvotes": 54,
      "mentions": 11,
      "mention_change": -8,
      "source_url": "https://feargreedmeter.com/top-100-most-popular-meme-stocks-today",
      "raw_text": "# 59 . SGOV iShares Trust - iShares 0-3 Month Treasury Bond ETF 54 11 -8"
    },
    {
      "fetched_at_local": "2026-07-14T18:38:54+02:00",
      "fetched_at_utc": "2026-07-14T16:38:54+00:00",
      "rank": 60,
      "ticker": "DC",
      "company_name": "Dakota Gold",
      "upvotes": -20,
      "mentions": 10,
      "mention_change": 4,
      "source_url": "https://feargreedmeter.com/top-100-most-popular-meme-stocks-today",
      "raw_text": "# 60 . DC Dakota Gold -20 10 + 4"
    },
    {
      "fetched_at_local": "2026-07-14T18:38:54+02:00",
      "fetched_at_utc": "2026-07-14T16:38:54+00:00",
      "rank": 61,
      "ticker": "XLF",
      "company_name": "SSgA Active Trust - SSgA Financial Select Sector SPDR",
      "upvotes": 12,
      "mentions": 10,
      "mention_change": 5,
      "source_url": "https://feargreedmeter.com/top-100-most-popular-meme-stocks-today",
      "raw_text": "# 61 . XLF SSgA Active Trust - SSgA Financial Select Sector SPDR 12 10 + 5"
    },
    {
      "fetched_at_local": "2026-07-14T18:38:54+02:00",
      "fetched_at_utc": "2026-07-14T16:38:54+00:00",
      "rank": 62,
      "ticker": "DEI",
      "company_name": "Douglas Emmett",
      "upvotes": -22,
      "mentions": 10,
      "mention_change": 10,
      "source_url": "https://feargreedmeter.com/top-100-most-popular-meme-stocks-today",
      "raw_text": "# 62 . DEI Douglas Emmett -22 10 + 10"
    },
    {
      "fetched_at_local": "2026-07-14T18:38:54+02:00",
      "fetched_at_utc": "2026-07-14T16:38:54+00:00",
      "rank": 63,
      "ticker": "ES",
      "company_name": "Eversource Energy",
      "upvotes": 21,
      "mentions": 10,
      "mention_change": -15,
      "source_url": "https://feargreedmeter.com/top-100-most-popular-meme-stocks-today",
      "raw_text": "# 63 . ES Eversource Energy 21 10 -15"
    },
    {
      "fetched_at_local": "2026-07-14T18:38:54+02:00",
      "fetched_at_utc": "2026-07-14T16:38:54+00:00",
      "rank": 64,
      "ticker": "SOXS",
      "company_name": "Direxion Shares ETF Trust - Direxion Daily Semiconductor Bear 3X Share",
      "upvotes": 14,
      "mentions": 9,
      "mention_change": 1,
      "source_url": "https://feargreedmeter.com/top-100-most-popular-meme-stocks-today",
      "raw_text": "# 64 . SOXS Direxion Shares ETF Trust - Direxion Daily Semiconductor Bear 3X Share 14 9 + 1"
    },
    {
      "fetched_at_local": "2026-07-14T18:38:54+02:00",
      "fetched_at_utc": "2026-07-14T16:38:54+00:00",
      "rank": 65,
      "ticker": "ET",
      "company_name": "Energy Transfer Partners",
      "upvotes": 88,
      "mentions": 9,
      "mention_change": -3,
      "source_url": "https://feargreedmeter.com/top-100-most-popular-meme-stocks-today",
      "raw_text": "# 65 . ET Energy Transfer Partners 88 9 -3"
    },
    {
      "fetched_at_local": "2026-07-14T18:38:54+02:00",
      "fetched_at_utc": "2026-07-14T16:38:54+00:00",
      "rank": 66,
      "ticker": "UNH",
      "company_name": "UnitedHealth",
      "upvotes": 30,
      "mentions": 9,
      "mention_change": 4,
      "source_url": "https://feargreedmeter.com/top-100-most-popular-meme-stocks-today",
      "raw_text": "# 66 . UNH UnitedHealth 30 9 + 4"
    },
    {
      "fetched_at_local": "2026-07-14T18:38:54+02:00",
      "fetched_at_utc": "2026-07-14T16:38:54+00:00",
      "rank": 67,
      "ticker": "AFL",
      "company_name": "Aflac",
      "upvotes": 81,
      "mentions": 9,
      "mention_change": 9,
      "source_url": "https://feargreedmeter.com/top-100-most-popular-meme-stocks-today",
      "raw_text": "# 67 . AFL Aflac 81 9 + 9"
    },
    {
      "fetched_at_local": "2026-07-14T18:38:54+02:00",
      "fetched_at_utc": "2026-07-14T16:38:54+00:00",
      "rank": 68,
      "ticker": "ARM",
      "company_name": "Arm Holdings",
      "upvotes": 16,
      "mentions": 8,
      "mention_change": 7,
      "source_url": "https://feargreedmeter.com/top-100-most-popular-meme-stocks-today",
      "raw_text": "# 68 . ARM Arm Holdings 16 8 + 7"
    },
    {
      "fetched_at_local": "2026-07-14T18:38:54+02:00",
      "fetched_at_utc": "2026-07-14T16:38:54+00:00",
      "rank": 69,
      "ticker": "HTZ",
      "company_name": "Hertz",
      "upvotes": 17,
      "mentions": 8,
      "mention_change": 8,
      "source_url": "https://feargreedmeter.com/top-100-most-popular-meme-stocks-today",
      "raw_text": "# 69 . HTZ Hertz 17 8 + 8"
    },
    {
      "fetched_at_local": "2026-07-14T18:38:54+02:00",
      "fetched_at_utc": "2026-07-14T16:38:54+00:00",
      "rank": 70,
      "ticker": "UP",
      "company_name": "Wheels Up",
      "upvotes": 33,
      "mentions": 8,
      "mention_change": -1,
      "source_url": "https://feargreedmeter.com/top-100-most-popular-meme-stocks-today",
      "raw_text": "# 70 . UP Wheels Up 33 8 -1"
    },
    {
      "fetched_at_local": "2026-07-14T18:38:54+02:00",
      "fetched_at_utc": "2026-07-14T16:38:54+00:00",
      "rank": 71,
      "ticker": "FCF",
      "company_name": "First Commonwealth Financial Corp",
      "upvotes": 48,
      "mentions": 8,
      "mention_change": 5,
      "source_url": "https://feargreedmeter.com/top-100-most-popular-meme-stocks-today",
      "raw_text": "# 71 . FCF First Commonwealth Financial Corp 48 8 + 5"
    },
    {
      "fetched_at_local": "2026-07-14T18:38:54+02:00",
      "fetched_at_utc": "2026-07-14T16:38:54+00:00",
      "rank": 72,
      "ticker": "MSTR",
      "company_name": "MicroStrategy",
      "upvotes": 17,
      "mentions": 8,
      "mention_change": -1,
      "source_url": "https://feargreedmeter.com/top-100-most-popular-meme-stocks-today",
      "raw_text": "# 72 . MSTR MicroStrategy 17 8 -1"
    },
    {
      "fetched_at_local": "2026-07-14T18:38:54+02:00",
      "fetched_at_utc": "2026-07-14T16:38:54+00:00",
      "rank": 73,
      "ticker": "TLT",
      "company_name": "BlackRock Institutional Trust Company N.A. - BTC iShares 20+ Year Trea",
      "upvotes": 15,
      "mentions": 8,
      "mention_change": 7,
      "source_url": "https://feargreedmeter.com/top-100-most-popular-meme-stocks-today",
      "raw_text": "# 73 . TLT BlackRock Institutional Trust Company N.A. - BTC iShares 20+ Year Trea 15 8 + 7"
    },
    {
      "fetched_at_local": "2026-07-14T18:38:54+02:00",
      "fetched_at_utc": "2026-07-14T16:38:54+00:00",
      "rank": 74,
      "ticker": "SOXX",
      "company_name": "BlackRock Institutional Trust Company N.A. - BTC iShares PHLX Semicond",
      "upvotes": 16,
      "mentions": 8,
      "mention_change": 3,
      "source_url": "https://feargreedmeter.com/top-100-most-popular-meme-stocks-today",
      "raw_text": "# 74 . SOXX BlackRock Institutional Trust Company N.A. - BTC iShares PHLX Semicond 16 8 + 3"
    },
    {
      "fetched_at_local": "2026-07-14T18:38:54+02:00",
      "fetched_at_utc": "2026-07-14T16:38:54+00:00",
      "rank": 75,
      "ticker": "SMA",
      "company_name": "SmartStop Self Storage REIT",
      "upvotes": 21,
      "mentions": 7,
      "mention_change": 6,
      "source_url": "https://feargreedmeter.com/top-100-most-popular-meme-stocks-today",
      "raw_text": "# 75 . SMA SmartStop Self Storage REIT 21 7 + 6"
    },
    {
      "fetched_at_local": "2026-07-14T18:38:54+02:00",
      "fetched_at_utc": "2026-07-14T16:38:54+00:00",
      "rank": 76,
      "ticker": "IREN",
      "company_name": "Iris Energy",
      "upvotes": 21,
      "mentions": 7,
      "mention_change": 6,
      "source_url": "https://feargreedmeter.com/top-100-most-popular-meme-stocks-today",
      "raw_text": "# 76 . IREN Iris Energy 21 7 + 6"
    },
    {
      "fetched_at_local": "2026-07-14T18:38:54+02:00",
      "fetched_at_utc": "2026-07-14T16:38:54+00:00",
      "rank": 77,
      "ticker": "APP",
      "company_name": "AppLovin",
      "upvotes": 12,
      "mentions": 7,
      "mention_change": 4,
      "source_url": "https://feargreedmeter.com/top-100-most-popular-meme-stocks-today",
      "raw_text": "# 77 . APP AppLovin 12 7 + 4"
    },
    {
      "fetched_at_local": "2026-07-14T18:38:54+02:00",
      "fetched_at_utc": "2026-07-14T16:38:54+00:00",
      "rank": 78,
      "ticker": "EWY",
      "company_name": "BlackRock Institutional Trust Company N.A. - iShares MSCI South Korea",
      "upvotes": 21,
      "mentions": 7,
      "mention_change": 1,
      "source_url": "https://feargreedmeter.com/top-100-most-popular-meme-stocks-today",
      "raw_text": "# 78 . EWY BlackRock Institutional Trust Company N.A. - iShares MSCI South Korea 21 7 + 1"
    },
    {
      "fetched_at_local": "2026-07-14T18:38:54+02:00",
      "fetched_at_utc": "2026-07-14T16:38:54+00:00",
      "rank": 79,
      "ticker": "BB",
      "company_name": "BlackBerry",
      "upvotes": 15,
      "mentions": 7,
      "mention_change": -1,
      "source_url": "https://feargreedmeter.com/top-100-most-popular-meme-stocks-today",
      "raw_text": "# 79 . BB BlackBerry 15 7 -1"
    },
    {
      "fetched_at_local": "2026-07-14T18:38:54+02:00",
      "fetched_at_utc": "2026-07-14T16:38:54+00:00",
      "rank": 80,
      "ticker": "TDS",
      "company_name": "Telephone and Data Systems",
      "upvotes": null,
      "mentions": 7,
      "mention_change": 6,
      "source_url": "https://feargreedmeter.com/top-100-most-popular-meme-stocks-today",
      "raw_text": "# 80 . TDS Telephone and Data Systems 7 + 6"
    },
    {
      "fetched_at_local": "2026-07-14T18:38:54+02:00",
      "fetched_at_utc": "2026-07-14T16:38:54+00:00",
      "rank": 81,
      "ticker": "CLSK",
      "company_name": "CleanSpark",
      "upvotes": 24,
      "mentions": 7,
      "mention_change": 7,
      "source_url": "https://feargreedmeter.com/top-100-most-popular-meme-stocks-today",
      "raw_text": "# 81 . CLSK CleanSpark 24 7 + 7"
    },
    {
      "fetched_at_local": "2026-07-14T18:38:54+02:00",
      "fetched_at_utc": "2026-07-14T16:38:54+00:00",
      "rank": 82,
      "ticker": "IQ",
      "company_name": "iQIYI",
      "upvotes": -4,
      "mentions": 7,
      "mention_change": -1,
      "source_url": "https://feargreedmeter.com/top-100-most-popular-meme-stocks-today",
      "raw_text": "# 82 . IQ iQIYI -4 7 -1"
    },
    {
      "fetched_at_local": "2026-07-14T18:38:54+02:00",
      "fetched_at_utc": "2026-07-14T16:38:54+00:00",
      "rank": 83,
      "ticker": "ON",
      "company_name": "ON Semiconductor",
      "upvotes": 25,
      "mentions": 7,
      "mention_change": 4,
      "source_url": "https://feargreedmeter.com/top-100-most-popular-meme-stocks-today",
      "raw_text": "# 83 . ON ON Semiconductor 25 7 + 4"
    },
    {
      "fetched_at_local": "2026-07-14T18:38:54+02:00",
      "fetched_at_utc": "2026-07-14T16:38:54+00:00",
      "rank": 84,
      "ticker": "MS",
      "company_name": "Morgan Stanley",
      "upvotes": 25,
      "mentions": 7,
      "mention_change": 3,
      "source_url": "https://feargreedmeter.com/top-100-most-popular-meme-stocks-today",
      "raw_text": "# 84 . MS Morgan Stanley 25 7 + 3"
    },
    {
      "fetched_at_local": "2026-07-14T18:38:54+02:00",
      "fetched_at_utc": "2026-07-14T16:38:54+00:00",
      "rank": 85,
      "ticker": "IP",
      "company_name": "International Paper",
      "upvotes": 3,
      "mentions": 7,
      "mention_change": -5,
      "source_url": "https://feargreedmeter.com/top-100-most-popular-meme-stocks-today",
      "raw_text": "# 85 . IP International Paper 3 7 -5"
    },
    {
      "fetched_at_local": "2026-07-14T18:38:54+02:00",
      "fetched_at_utc": "2026-07-14T16:38:54+00:00",
      "rank": 86,
      "ticker": "PYPL",
      "company_name": "PayPal",
      "upvotes": 3,
      "mentions": 7,
      "mention_change": 6,
      "source_url": "https://feargreedmeter.com/top-100-most-popular-meme-stocks-today",
      "raw_text": "# 86 . PYPL PayPal 3 7 + 6"
    },
    {
      "fetched_at_local": "2026-07-14T18:38:54+02:00",
      "fetched_at_utc": "2026-07-14T16:38:54+00:00",
      "rank": 87,
      "ticker": "SUNE",
      "company_name": "SUNation Energy Inc.",
      "upvotes": 13,
      "mentions": 6,
      "mention_change": 6,
      "source_url": "https://feargreedmeter.com/top-100-most-popular-meme-stocks-today",
      "raw_text": "# 87 . SUNE SUNation Energy Inc. 13 6 + 6"
    },
    {
      "fetched_at_local": "2026-07-14T18:38:54+02:00",
      "fetched_at_utc": "2026-07-14T16:38:54+00:00",
      "rank": 88,
      "ticker": "OS",
      "company_name": "OneStream",
      "upvotes": 19,
      "mentions": 6,
      "mention_change": -1,
      "source_url": "https://feargreedmeter.com/top-100-most-popular-meme-stocks-today",
      "raw_text": "# 88 . OS OneStream 19 6 -1"
    },
    {
      "fetched_at_local": "2026-07-14T18:38:54+02:00",
      "fetched_at_utc": "2026-07-14T16:38:54+00:00",
      "rank": 89,
      "ticker": "RR",
      "company_name": "Richtech Robotics",
      "upvotes": 32,
      "mentions": 6,
      "mention_change": 2,
      "source_url": "https://feargreedmeter.com/top-100-most-popular-meme-stocks-today",
      "raw_text": "# 89 . RR Richtech Robotics 32 6 + 2"
    },
    {
      "fetched_at_local": "2026-07-14T18:38:54+02:00",
      "fetched_at_utc": "2026-07-14T16:38:54+00:00",
      "rank": 90,
      "ticker": "LINK",
      "company_name": "Interlink Electronics",
      "upvotes": 7,
      "mentions": 6,
      "mention_change": 4,
      "source_url": "https://feargreedmeter.com/top-100-most-popular-meme-stocks-today",
      "raw_text": "# 90 . LINK Interlink Electronics 7 6 + 4"
    },
    {
      "fetched_at_local": "2026-07-14T18:38:54+02:00",
      "fetched_at_utc": "2026-07-14T16:38:54+00:00",
      "rank": 91,
      "ticker": "APLD",
      "company_name": "Applied Blockchain",
      "upvotes": 57,
      "mentions": 6,
      "mention_change": 0,
      "source_url": "https://feargreedmeter.com/top-100-most-popular-meme-stocks-today",
      "raw_text": "# 91 . APLD Applied Blockchain 57 6 + 0"
    },
    {
      "fetched_at_local": "2026-07-14T18:38:54+02:00",
      "fetched_at_utc": "2026-07-14T16:38:54+00:00",
      "rank": 92,
      "ticker": "CD",
      "company_name": "Chindata",
      "upvotes": 19,
      "mentions": 6,
      "mention_change": 5,
      "source_url": "https://feargreedmeter.com/top-100-most-popular-meme-stocks-today",
      "raw_text": "# 92 . CD Chindata 19 6 + 5"
    },
    {
      "fetched_at_local": "2026-07-14T18:38:54+02:00",
      "fetched_at_utc": "2026-07-14T16:38:54+00:00",
      "rank": 93,
      "ticker": "TQQQ",
      "company_name": "ProShares Trust - ProShares UltraPro QQQ",
      "upvotes": 8,
      "mentions": 6,
      "mention_change": 5,
      "source_url": "https://feargreedmeter.com/top-100-most-popular-meme-stocks-today",
      "raw_text": "# 93 . TQQQ ProShares Trust - ProShares UltraPro QQQ 8 6 + 5"
    },
    {
      "fetched_at_local": "2026-07-14T18:38:54+02:00",
      "fetched_at_utc": "2026-07-14T16:38:54+00:00",
      "rank": 94,
      "ticker": "SLV",
      "company_name": "iShares Silver Trust",
      "upvotes": 8,
      "mentions": 6,
      "mention_change": 4,
      "source_url": "https://feargreedmeter.com/top-100-most-popular-meme-stocks-today",
      "raw_text": "# 94 . SLV iShares Silver Trust 8 6 + 4"
    },
    {
      "fetched_at_local": "2026-07-14T18:38:54+02:00",
      "fetched_at_utc": "2026-07-14T16:38:54+00:00",
      "rank": 95,
      "ticker": "VTI",
      "company_name": "Vanguard Total Stock Market ETF",
      "upvotes": 9,
      "mentions": 6,
      "mention_change": -10,
      "source_url": "https://feargreedmeter.com/top-100-most-popular-meme-stocks-today",
      "raw_text": "# 95 . VTI Vanguard Total Stock Market ETF 9 6 -10"
    },
    {
      "fetched_at_local": "2026-07-14T18:38:54+02:00",
      "fetched_at_utc": "2026-07-14T16:38:54+00:00",
      "rank": 96,
      "ticker": "VT",
      "company_name": "Vanguard Group, Inc. - Vanguard Total World Stock ETF",
      "upvotes": 25,
      "mentions": 6,
      "mention_change": 1,
      "source_url": "https://feargreedmeter.com/top-100-most-popular-meme-stocks-today",
      "raw_text": "# 96 . VT Vanguard Group, Inc. - Vanguard Total World Stock ETF 25 6 + 1"
    },
    {
      "fetched_at_local": "2026-07-14T18:38:54+02:00",
      "fetched_at_utc": "2026-07-14T16:38:54+00:00",
      "rank": 97,
      "ticker": "SCHD",
      "company_name": "Schwab Strategic Trust - CSIM Schwab US Dividend Equity ETF",
      "upvotes": 10,
      "mentions": 6,
      "mention_change": 3,
      "source_url": "https://feargreedmeter.com/top-100-most-popular-meme-stocks-today",
      "raw_text": "# 97 . SCHD Schwab Strategic Trust - CSIM Schwab US Dividend Equity ETF 10 6 + 3"
    },
    {
      "fetched_at_local": "2026-07-14T18:38:54+02:00",
      "fetched_at_utc": "2026-07-14T16:38:54+00:00",
      "rank": 98,
      "ticker": "IBKR",
      "company_name": "Interactive Brokers",
      "upvotes": 13,
      "mentions": 6,
      "mention_change": -4,
      "source_url": "https://feargreedmeter.com/top-100-most-popular-meme-stocks-today",
      "raw_text": "# 98 . IBKR Interactive Brokers 13 6 -4"
    },
    {
      "fetched_at_local": "2026-07-14T18:38:54+02:00",
      "fetched_at_utc": "2026-07-14T16:38:54+00:00",
      "rank": 99,
      "ticker": "HR",
      "company_name": "Healthcare Realty",
      "upvotes": 37,
      "mentions": 6,
      "mention_change": 5,
      "source_url": "https://feargreedmeter.com/top-100-most-popular-meme-stocks-today",
      "raw_text": "# 99 . HR Healthcare Realty 37 6 + 5"
    },
    {
      "fetched_at_local": "2026-07-14T18:38:54+02:00",
      "fetched_at_utc": "2026-07-14T16:38:54+00:00",
      "rank": 100,
      "ticker": "AVAV",
      "company_name": "AeroVironment",
      "upvotes": 25,
      "mentions": 6,
      "mention_change": 3,
      "source_url": "https://feargreedmeter.com/top-100-most-popular-meme-stocks-today",
      "raw_text": "# 100 . AVAV AeroVironment 25 6 + 3"
    }
  ]
}